Workbook

Sheet cleaned_data
A1: sme_id | B1: sme_name | C1: province | D1: local_municipality | E1: setting | F1: primary_crop | G1: years_in_operation | H1: num_employees | I1: owner_gender | J1: owner_age_range | K1: business_registration_status | L1: financial_statements_prepared | M1: separate_bank_account | N1: land_ownership_type | O1: title_deed | P1: previous_grant_or_investment | Q1: annual_production_volume_kg | R1: yoy_production_change_pct | S1: production_diversity_count | T1: post_harvest_loss_pct | U1: storage_access | V1: cold_chain_capacity | W1: distance_to_market_km | X1: num_buyers | Y1: formal_offtake_contracts | Z1: avg_price_per_kg_zar | AA1: unit_cost_per_kg_zar | AB1: gross_margin_pct | AC1: outstanding_loan_amount_zar | AD1: loan_repayment_status | AE1: debt_to_revenue_ratio | AF1: certification_status | AG1: export_readiness | AH1: drought_events_5yr | AI1: environmental_shocks_12mo | AJ1: irrigation_present | AK1: electricity_source | AL1: loadshedding_days_per_month | AM1: energy_mitigation_present | AN1: income_seasonality_risk | AO1: pct_women_leadership | AP1: pct_women_workforce | AQ1: pct_youth_employees | AR1: pct_hdi_employees | AS1: sources_from_women_farmers
A2: SME0001 | B2: Thando Boerdery | C2: Western Cape | D2: Hex River Valley | E2: Small town | F2: apples | G2: 19 | H2: 69 | I2: Female | J2: 18-30 | K2: Registered | L2: Yes | M2: Yes | N2: Owned | O2: Unknown | P2: CASP | Q2: 194629 | R2: -6 | S2: 5 | T2: 5.4 | U2: Yes | V2: Yes | W2: 219 | X2: 6 | Y2: Yes | Z2: 16.85 | AA2: 11.76 | AB2: 30.207715 | AC2: 0 | AD2: No Loan | AE2: 0 | AF2: GlobalG.A.P. | AG2: Yes | AH2: 2 | AI2: 1 | AJ2: Yes | AK2: Eskom grid | AL2: 20 | AM2: Yes | AN2: Low | AO2: 35.9 | AP2: 34.1 | AQ2: 16.9 | AR2: 42.6 | AS2: No
A3: SME0002 | B3: Tlhaga Morning | C3: Western Cape | D3: Grabouw | E3: Peri-urban | F3: peaches | G3: 3 | H3: 44 | I3: Female | J3: 51-60 | K3: Registered | L3: Yes | M3: Yes | N3: Owned | O3: Yes | P3: MAFISA | Q3: 317717 | R3: 18.1 | S3: 3 | T3: 7.4 | U3: Yes | V3: Yes | W3: 41 | X3: 12 | Y3: Yes | Z3: 26.83 | AA3: 12.02 | AB3: 55.199404 | AC3: 215958 | AD3: Settled | AE3: 0.025334257 | AF3: Unknown | AG3: No | AH3: 0 | AI3: 1 | AJ3: Yes | AK3: Eskom grid | AL3: 20 | AM3: Yes | AN3: Medium | AO3: 91.3 | AP3: 49.7 | AQ3: 37.3 | AR3: 52.8 | AS3: No
A4: SME0003 | B4: Vhembe Red | C4: Western Cape | D4: Ceres | E4: Small town | F4: pears | G4: 12 | H4: 43 | I4: Male | J4: 60+ | K4: Registered | L4: Yes | M4: Yes | N4: State land | O4: No | P4: Agri-BEE | Q4: 127662 | R4: 25.3 | S4: 1 | T4: 7.3 | U4: Yes | V4: Yes | W4: 37 | X4: 9 | Y4: Yes | Z4: 44.85 | AA4: 25.19 | AB4: 43.835006 | AC4: 0 | AD4: No Loan | AE4: 0 | AF4: Checkers Good Farming | AG4: Yes | AH4: 0 | AI4: 2 | AJ4: Yes | AK4: Solar | AL4: 0 | AM4: Yes | AN4: High | AO4: 0.3 | AP4: 60.5 | AQ4: 37.4 | AR4: 98.3 | AS4: No
A5: SME0004 | B5: Tsebo Red | C5: Western Cape | D5: Ceres | E5: Peri-urban | F5: pears | G5: 20 | H5: 56 | I5: Male | J5: 18-30 | K5: Registered | L5: Yes | M5: Yes | N5: Owned | O5: Yes | P5: CASP | Q5: 270306 | R5: 32.7 | S5: 3 | T5: 8.6 | U5: Yes | V5: Unknown | W5: 45 | X5: 4 | Y5: Yes | Z5: 37.82 | AA5: 28.03 | AB5: 25.885775 | AC5: 100608 | AD5: Settled | AE5: 0.0098413642 | AF5: GlobalG.A.P. | AG5: Yes | AH5: 4 | AI5: 3 | AJ5: Yes | AK5: Eskom grid | AL5: 22 | AM5: No | AN5: Medium | AO5: 71.3 | AP5: 37.9 | AQ5: 35.2 | AR5: 62.4 | AS5: No
A6: SME0005 | B6: Silver Valley | C6: Western Cape | D6: Ceres | E6: Peri-urban | F6: apples | G6: 8 | H6: 23 | I6: Female | J6: 41-50 | K6: Registered | L6: Yes | M6: Yes | N6: Owned | O6: Yes | P6: CASP | Q6: 349565 | R6: -5.7 | S6: 4 | T6: 8.2 | U6: Yes | V6: No | W6: 247 | X6: 6 | Y6: No | Z6: 37.49 | AA6: 15.98 | AB6: 57.3753 | AC6: 344841 | AD6: Current | AE6: 0.026313312 | AF6: Checkers Good Farming | AG6: Yes | AH6: 0 | AI6: 0 | AJ6: Yes | AK6: Solar | AM6: No | AN6: Low | AO6: 24.9 | AP6: 23.3 | AQ6: 25.2 | AR6: 65.3 | AS6: Yes
A7: SME0006 | B7: Tshivhase Silver | C7: Western Cape | D7: Hex River Valley | E7: Small town | F7: apples | G7: 6 | H7: 67 | I7: Male | J7: 51-60 | K7: Informal | L7: Yes | M7: No | N7: Leased | O7: No | P7: LRAD | Q7: 290260 | S7: 2 | T7: 10.7 | U7: No | V7: No | W7: 140 | X7: 10 | Y7: Yes | Z7: 33.17 | AA7: 21.3 | AB7: 35.785348 | AC7: 0 | AD7: No Loan | AE7: 0 | AF7: Woolworths TNC | AG7: Yes | AH7: 1 | AI7: 2 | AJ7: Yes | AK7: Eskom grid | AL7: 8 | AM7: Yes | AN7: High | AO7: 5.7 | AP7: 50.9 | AQ7: 27.6 | AR7: 91.2 | AS7: Yes
A8: SME0007 | B8: Amandla Golden | C8: Western Cape | D8: Hex River Valley | E8: Rural | F8: peaches | G8: 19 | H8: 91 | I8: Female | J8: 60+ | K8: Registered | L8: Yes | M8: Yes | N8: Leased | O8: Unknown | P8: CASP | Q8: 299794 | R8: 19.4 | S8: 5 | T8: 12.8 | U8: No | V8: No | W8: 109 | X8: 8 | Y8: Yes | Z8: 21.44 | AA8: 13.26 | AB8: 38.152985 | AC8: 252942 | AD8: Current | AE8: 0.039352582 | AF8: GlobalG.A.P. | AG8: No | AH8: 4 | AI8: 0 | AJ8: Yes | AK8: Eskom grid | AL8: 16 | AM8: Yes | AN8: High | AO8: 88.1 | AP8: 71.5 | AQ8: 21.6 | AR8: 49.5 | AS8: No
A9: SME0008 | B9: Ubuntu Plaas | C9: Western Cape | D9: Hex River Valley | E9: Peri-urban | F9: tomatoes | G9: 23 | H9: 58 | I9: Male | J9: 41-50 | K9: Registered | L9: Yes | M9: Yes | N9: Leased | O9: Yes | P9: DTIC | Q9: 336131 | R9: -4.9 | S9: 1 | T9: 6.4 | U9: Yes | V9: Yes | W9: 6 | X9: 8 | Y9: No | Z9: 30.85 | AA9: 14.03 | AB9: 54.52188 | AC9: 0 | AD9: No Loan | AE9: 0 | AF9: Fairtrade | AG9: Yes | AH9: 0 | AI9: 0 | AJ9: Yes | AK9: Eskom grid | AL9: 22 | AM9: Yes | AN9: Low | AO9: 83.5 | AP9: 50.8 | AQ9: 11.7 | AR9: 47.6 | AS9: Yes
A10: SME0009 | B10: Mashamba Rainbow | C10: Western Cape | D10: Ceres | E10: Peri-urban | F10: apples | G10: 8 | H10: 10 | I10: Male | J10: 51-60 | K10: Registered | L10: No | M10: Yes | N10: Leased | O10: Yes | P10: CASP | Q10: 174036 | R10: 24.2 | S10: 3 | T10: 16.7 | U10: Yes | V10: Yes | W10: 132 | X10: 7 | Y10: Yes | Z10: 33.35 | AA10: 16.78 | AB10: 49.685157 | AC10: 376552 | AD10: Current | AE10: 0.064876891 | AF10: SIZA | AG10: No | AH10: 1 | AI10: 1 | AJ10: Yes | AK10: Eskom grid | AL10: 18 | AM10: Yes | AN10: Low | AO10: 96.7 | AP10: 29.5 | AQ10: 33.9 | AR10: 64 | AS10: No
A11: SME0010 | B11: Green Valley | C11: Western Cape | D11: Hex River Valley | E11: Rural | F11: table grapes | G11: 24 | H11: 115 | I11: Male | J11: 51-60 | K11: Registered | L11: No | M11: Yes | N11: Owned | O11: Yes | P11: DTIC | Q11: 5000 | R11: -13.1 | S11: 5 | T11: 7.9 | U11: Yes | V11: Yes | W11: 271 | X11: 11 | Y11: Yes | Z11: 42.67 | AA11: 27.51 | AB11: 35.528474 | AC11: 345038 | AD11: Current | AE11: 1.6172393 | AF11: Woolworths TNC | AG11: No | AH11: 0 | AI11: 2 | AJ11: Yes | AK11: Generator | AL11: 6 | AM11: Yes | AN11: High | AO11: 55.4 | AP11: 23.4 | AQ11: 34.9 | AR11: 62.7 | AS11: No
A12: SME0011 | B12: Siyabonga Plaas | C12: Western Cape | D12: Hex River Valley | E12: Peri-urban | F12: table grapes | G12: 15 | H12: 101 | I12: Male | J12: 60+ | K12: Registered | L12: Yes | M12: Yes | N12: Owned | O12: Unknown | P12: Agri-BEE | Q12: 496145 | R12: 34.1 | S12: 2 | T12: 14.9 | U12: Yes | V12: Yes | W12: 176 | X12: 4 | Y12: No | Z12: 35.29 | AA12: 21.85 | AB12: 38.084443 | AC12: 159304 | AD12: In Arrears | AE12: 0.0090984289 | AF12: Organic (CERES) | AG12: No | AH12: 0 | AI12: 3 | AJ12: Yes | AK12: Solar | AL12: 0 | AM12: Yes | AN12: High | AO12: 49.4 | AP12: 27.1 | AQ12: 34.5 | AR12: 40.3 | AS12: No
A13: SME0012 | B13: Silver Valley | C13: Western Cape | D13: Ceres | E13: Peri-urban | F13: avocados | G13: 22 | H13: 82 | I13: Male | J13: 51-60 | K13: Registered | L13: Yes | M13: Yes | N13: Owned | O13: Yes | P13: DTIC | Q13: 457106 | R13: 33.5 | S13: 4 | T13: 17.5 | U13: Yes | V13: No | W13: 248 | X13: 10 | Y13: Yes | Z13: 15.64 | AA13: 9.46 | AB13: 39.514066 | AC13: 0 | AD13: No Loan | AE13: 0 | AF13: Fairtrade | AG13: No | AH13: 2 | AI13: 3 | AJ13: Yes | AK13: Eskom grid | AL13: 19 | AM13: Yes | AN13: High | AO13: 89.3 | AP13: 15.6 | AQ13: 11.8 | AR13: 63 | AS13: Yes
A14: SME0013 | B14: Lentswe Sunrise | C14: Western Cape | D14: Villiersdorp | E14: Small town | F14: table grapes | G14: 28 | H14: 112 | I14: Male | J14: 51-60 | K14: Registered | L14: No | M14: Yes | N14: Owned | O14: Yes | P14: CASP | Q14: 264422 | R14: -2.1 | S14: 4 | T14: 17.8 | U14: No | V14: No | W14: 219 | X14: 11 | Y14: Yes | Z14: 27.3 | AA14: 16.14 | AB14: 40.879121 | AC14: 175537 | AD14: Current | AE14: 0.024316913 | AF14: GlobalG.A.P. | AG14: No | AH14: 3 | AI14: 1 | AJ14: Yes | AK14: Solar | AL14: 0 | AM14: No | AN14: Low | AO14: 90.7 | AP14: 51.4 | AQ14: 34.8 | AR14: 45 | AS14: No
A15: SME0014 | B15: Mupo Thando | C15: Western Cape | D15: Grabouw | E15: Peri-urban | F15: plums | G15: 9 | H15: 25 | I15: Male | J15: 18-30 | K15: Registered | L15: Yes | M15: Yes | N15: Owned | O15: Yes | P15: None | Q15: 362810 | R15: -16.9 | S15: 3 | T15: 8.4 | U15: Yes | V15: No | W15: 25 | X15: 3 | Y15: No | Z15: 13.78 | AA15: 4.94 | AB15: 64.150943 | AC15: 100977 | AD15: Settled | AE15: 0.020197332 | AF15: Organic (CERES) | AG15: Yes | AH15: 2 | AI15: 2 | AJ15: Yes | AK15: Eskom grid | AL15: 17 | AM15: No | AN15: Low | AO15: 77.8 | AP15: 21.5 | AQ15: 19 | AR15: 74.7 | AS15: No
A16: SME0015 | B16: Tlhaga Thando | C16: Western Cape | D16: Ceres | E16: Small town | F16: apples | G16: 26 | H16: 87 | I16: Female | J16: N/A | K16: Registered | L16: Yes | M16: Yes | N16: Owned | O16: No | P16: DTIC | Q16: 304593 | R16: 19.7 | S16: 1 | T16: 12.6 | U16: Yes | V16: Unknown | W16: 255 | X16: 4 | Y16: Yes | Z16: 20.13 | AA16: 14.22 | AB16: 29.359165 | AC16: 122393 | AD16: Settled | AE16: 0.019961487 | AF16: Organic (CERES) | AG16: Yes | AH16: 4 | AI16: 3 | AJ16: Yes | AK16: Solar | AL16: 0 | AM16: No | AN16: High | AO16: 32.2 | AP16: 27.2 | AQ16: 47.1 | AR16: 56.7 | AS16: No
A17: SME0016 | B17: Sunrise Plaas | C17: Western Cape | D17: Hex River Valley | E17: Peri-urban | F17: plums | G17: 18 | H17: 16 | I17: Male | J17: 18-30 | K17: Registered | L17: Yes | M17: Yes | N17: Owned | O17: Yes | P17: LRAD | Q17: 457526 | R17: 4.4 | S17: 5 | T17: 16.4 | U17: Yes | V17: Yes | W17: 256 | X17: 10 | Y17: No | Z17: 9.63 | AA17: 4.22 | AB17: 56.178609 | AC17: 0 | AD17: No Loan | AE17: 0 | AF17: SIZA | AG17: No | AH17: 3 | AI17: 2 | AJ17: No | AK17: Solar | AL17: 0 | AM17: Yes | AN17: High | AO17: 70.3 | AP17: 29 | AQ17: 16.3 | AR17: 47.2 | AS17: Yes
A18: SME0017 | B18: Tshivhase Siyabonga | C18: Western Cape | D18: Ceres | E18: Peri-urban | F18: plums | G18: 27 | H18: 39 | I18: Male | J18: 31-40 | K18: Registered | L18: No | M18: Yes | N18: Owned | O18: Yes | P18: MAFISA | Q18: 174079 | R18: -1.9 | S18: 5 | T18: 6.9 | U18: Yes | V18: Yes | W18: 154 | X18: 5 | Y18: Yes | Z18: 35.36 | AA18: 13.83 | AB18: 60.888009 | AC18: 227471 | AD18: Current | AE18: 0.036954506 | AF18: Unknown | AG18: Yes | AH18: 3 | AI18: 0 | AJ18: Yes | AK18: Eskom grid | AL18: 14 | AM18: Yes | AN18: Low | AO18: 15.2 | AP18: 66.8 | AQ18: 47.7 | AR18: 45.1 | AS18: Yes
A19: SME0018 | B19: Mupo Green | C19: Western Cape | D19: Villiersdorp | E19: Peri-urban | F19: plums | G19: 20 | H19: 109 | I19: Female | J19: 31-40 | K19: Registered | L19: No | M19: Yes | N19: Owned | O19: Yes | P19: None | Q19: 190637 | R19: -4.1 | S19: 1 | T19: 7.4 | U19: Yes | V19: Yes | W19: 6 | X19: 9 | Y19: Yes | Z19: 29.16 | AA19: 13.6 | AB19: 53.360768 | AC19: 565565 | AD19: Current | AE19: 0.10173908 | AF19: GlobalG.A.P. | AG19: Yes | AH19: 2 | AI19: 1 | AJ19: Yes | AK19: Solar | AL19: 0 | AM19: Yes | AN19: Medium | AO19: 90.8 | AP19: 67.9 | AQ19: 8.2 | AR19: 50 | AS19: Yes
... A22: SME0021 | B22: Tlhaga Blue | C22: Western Cape | D22: Grabouw | E22: Small town | F22: peaches | G22: 13 | H22: 39 | I22: Male | J22: 18-30 | K22: Registered | L22: Yes | M22: No | N22: Leased | O22: Yes | P22: MAFISA | Q22: 485104 | R22: 27.4 | S22: 4 | T22: 10.1 | U22: Yes | V22: Yes | W22: 6 | X22: 7 | Y22: Yes | Z22: 38.66 | AA22: 22.5 | AB22: 41.80031 | AC22: 0 | AD22: No Loan | AE22: 0 | AF22: Checkers Good Farming | AG22: Yes | AH22: 3 | AI22: 2 | AJ22: Yes | AK22: Solar | AL22: 0 | AM22: Yes | AN22: High | AO22: 93.3 | AP22: 70.9 | AQ22: 49.1 | AR22: 54.3 | AS22: No
A23: SME0022 | B23: Silver Valley | C23: Western Cape | D23: Villiersdorp | E23: Peri-urban | F23: plums | G23: 5 | H23: 79 | I23: Male | J23: 18-30 | K23: Informal | L23: Yes | M23: Yes | N23: Owned | O23: Yes | P23: Agri-BEE | Q23: 132277 | S23: 4 | T23: 5.2 | U23: Yes | V23: No | W23: 84 | X23: 4 | Y23: Yes | Z23: 43.8 | AA23: 21.26 | AB23: 51.461187 | AC23: 0 | AD23: No Loan | AE23: 0 | AF23: Woolworths TNC | AG23: No | AH23: 4 | AI23: 3 | AJ23: Yes | AK23: Solar | AL23: 0 | AM23: No | AN23: High | AO23: 87.2 | AP23: 12.5 | AQ23: 8.1 | AR23: 77.9 | AS23: No
A24: SME0023 | B24: Lentswe Themba | C24: Western Cape | D24: Hex River Valley | E24: Peri-urban | F24: apples | G24: 10 | H24: 60 | I24: Male | J24: 51-60 | K24: Registered | L24: Yes | M24: Yes | N24: Owned | O24: Yes | P24: LRAD | Q24: 208029 | S24: 5 | T24: 15.2 | U24: Yes | V24: Yes | W24: 200 | X24: 12 | Y24: Yes | Z24: 25.41 | AA24: 14.82 | AB24: 41.676505 | AC24: 510324 | AD24: Settled | AE24: 0.096542257 | AF24: Unknown | AG24: No | AH24: 2 | AI24: 1 | AJ24: No | AK24: Eskom grid | AL24: 15 | AM24: Unknown | AN24: High | AO24: 63.9 | AP24: 39.7 | AQ24: 16.3 | AR24: 90.7 | AS24: Yes
A25: SME0024 | B25: Vhembe Ubuntu | C25: Western Cape | D25: Ceres | E25: Small town | F25: plums | G25: 9 | H25: 16 | I25: Female | J25: 60+ | K25: Registered | L25: No | M25: Yes | N25: Owned | O25: Yes | P25: None | Q25: 340428 | R25: 30 | S25: 3 | T25: 16.6 | U25: Yes | V25: No | W25: 117 | X25: 6 | Y25: Yes | Z25: 32.43 | AA25: 20.7 | AB25: 36.170213 | AC25: 0 | AD25: No Loan | AE25: 0 | AF25: GlobalG.A.P. | AG25: No | AH25: 0 | AI25: 2 | AJ25: Yes | AK25: Solar | AL25: 0 | AM25: Yes | AN25: Medium | AO25: 9 | AP25: 30.7 | AQ25: 38.6 | AR25: 50.5 | AS25: Yes
A26: SME0025 | B26: Izifundo Themba | C26: Western Cape | D26: Ceres | E26: Peri-urban | F26: table grapes | G26: 3 | H26: 33 | I26: Male | J26: 51-60 | K26: Registered | L26: Yes | M26: No | N26: State land | O26: No | P26: DTIC | Q26: 271771 | R26: -14.6 | S26: 4 | T26: 5.2 | U26: Yes | V26: Yes | W26: 139 | X26: 12 | Y26: Yes | Z26: 30.9 | AA26: 15.41 | AB26: 50.12945 | AC26: 0 | AD26: No Loan | AE26: 0 | AF26: Fairtrade | AG26: No | AH26: 4 | AI26: 2 | AJ26: Yes | AK26: Generator | AL26: 5 | AM26: Yes | AN26: High | AP26: 31.2 | AQ26: 23.4 | AR26: 48.4 | AS26: No
A27: SME0026 | B27: Tshivhase Heritage | C27: Limpopo | D27: Tzaneen | E27: Small town | F27: litchis | G27: 19 | H27: 110 | I27: Male | J27: 51-60 | K27: Registered | L27: Yes | M27: Yes | N27: Owned | O27: Yes | P27: None | Q27: 131915 | R27: 30 | S27: 5 | T27: 11.1 | U27: No | V27: No | W27: 21 | X27: 8 | Y27: Yes | Z27: 23.34 | AA27: 10.37 | AB27: 55.569837 | AC27: 784742 | AD27: Settled | AE27: 0.25487771 | AF27: SIZA | AG27: Yes | AH27: 1 | AI27: 0 | AJ27: Yes | AK27: Generator | AL27: 3 | AM27: Yes | AN27: Low | AO27: 5.1 | AP27: 33.3 | AQ27: 49.5 | AR27: 87.2 | AS27: Yes
A28: SME0027 | B28: Themba Laan | C28: Limpopo | D28: Letsitele | E28: Rural | F28: avocados | G28: 18 | H28: 47 | I28: Male | J28: 18-30 | K28: Registered | L28: Yes | M28: Yes | N28: Leased | O28: No | P28: None | Q28: 93516 | R28: -12.1 | S28: 3 | T28: 16.8 | U28: Yes | V28: Yes | W28: 94 | X28: 7 | Y28: Yes | Z28: 34.93 | AA28: 19.58 | AB28: 43.945033 | AC28: 0 | AD28: No Loan | AE28: 0 | AF28: Fairtrade | AG28: No | AH28: 4 | AI28: 0 | AJ28: Yes | AK28: Generator | AL28: 10 | AM28: Yes | AN28: High | AO28: 45.8 | AP28: 77.5 | AQ28: 7.7 | AR28: 68.7 | AS28: No
A29: SME0028 | B29: Mashamba Rainbow | C29: Limpopo | D29: Bela-Bela | E29: Rural | F29: mangoes | G29: 13 | H29: 91 | I29: Male | J29: 51-60 | K29: Registered | L29: Yes | M29: Yes | N29: Owned | O29: Yes | P29: DTIC | Q29: 397418 | R29: 5.8 | S29: 1 | T29: 17.8 | U29: Yes | V29: Yes | W29: 115 | X29: 9 | Y29: Yes | Z29: 14.91 | AA29: 7.24 | AB29: 51.441985 | AC29: 332792 | AD29: Current | AE29: 0.056162664 | AF29: SIZA | AG29: Yes | AH29: 1 | AI29: 3 | AJ29: Yes | AK29: Eskom grid | AL29: 9 | AM29: Yes | AN29: Low | AO29: 74.5 | AP29: 36.1 | AQ29: 10.9 | AR29: 43.6 | AS29: No
A30: SME0029 | B30: Morning Ridge | C30: Limpopo | D30: Bela-Bela | E30: Small town | F30: avocados | G30: 20 | H30: 54 | I30: Male | J30: 18-30 | K30: Informal | L30: Yes | M30: No | N30: Owned | O30: Yes | P30: DTIC | Q30: 346030 | R30: -7.2 | S30: 4 | T30: 8.4 | U30: Yes | V30: No | W30: 193 | X30: 4 | Y30: No | Z30: 28.39 | AA30: 19.1 | AB30: 32.72279 | AC30: 0 | AD30: No Loan | AE30: 0 | AF30: Organic (CERES) | AG30: No | AH30: 4 | AI30: 0 | AJ30: No | AK30: Solar | AL30: 0 | AM30: No | AN30: High | AO30: 2.9 | AP30: 29.1 | AQ30: 39.3 | AR30: 95.3 | AS30: No
A31: SME0030 | B31: Amandla Green | C31: Limpopo | D31: Bela-Bela | E31: Rural | F31: mangoes | G31: 14 | H31: 73 | I31: Male | J31: 31-40 | K31: Registered | L31: No | M31: Yes | N31: Owned | O31: Yes | P31: MAFISA | Q31: 23198 | R31: 23.3 | S31: 5 | T31: 13.9 | U31: Yes | V31: Yes | W31: 30 | X31: 4 | Y31: Yes | Z31: 31.82 | AA31: 17.32 | AB31: 45.568825 | AC31: 218533 | AD31: Current | AE31: 0.29605085 | AF31: SIZA | AG31: Yes | AH31: 4 | AI31: 3 | AJ31: Yes | AK31: Solar | AL31: 0 | AM31: Yes | AN31: High | AO31: 98.4 | AP31: 13.8 | AQ31: 14.2 | AR31: 96.7 | AS31: No
A32: SME0031 | B32: Tshivhase Red | C32: Limpopo | D32: Tzaneen | E32: Peri-urban | F32: mangoes | G32: 3 | H32: 65 | I32: Female | J32: 51-60 | K32: Registered | L32: Yes | M32: Yes | N32: Owned | O32: Yes | P32: CASP | Q32: 18587 | R32: 35.3 | S32: 3 | T32: 13.6 | U32: Yes | V32: Yes | W32: 218 | Y32: Yes | Z32: 6.81 | AA32: 3.27 | AB32: 51.982379 | AC32: 0 | AD32: No Loan | AE32: 0 | AF32: Woolworths TNC | AG32: No | AH32: 2 | AI32: 0 | AJ32: Yes | AK32: Generator | AL32: 3 | AM32: Yes | AN32: Low | AO32: 39.6 | AP32: 31.7 | AQ32: 20.3 | AR32: 60 | AS32: Yes
A33: SME0032 | B33: Andile Hoek | C33: Limpopo | D33: Levubu | E33: Small town | F33: avocados | G33: 7 | H33: 37 | I33: Male | J33: 18-30 | K33: Informal | L33: Yes | M33: Yes | N33: Owned | O33: Yes | P33: LRAD | Q33: 485194 | R33: 17.7 | S33: 4 | T33: 16.3 | U33: Yes | V33: Yes | W33: 170 | X33: 8 | Y33: Yes | Z33: 8.66 | AA33: 4.56 | AB33: 47.344111 | AC33: 219739 | AD33: In Arrears | AE33: 0.052296645 | AF33: SIZA | AG33: Yes | AH33: 0 | AI33: 2 | AJ33: Yes | AK33: Eskom grid | AL33: 9 | AM33: No | AN33: Low | AO33: 61.5 | AP33: 45.5 | AQ33: 25.8 | AR33: 73.3 | AS33: No
A34: SME0033 | B34: Lentswe Morning | C34: Limpopo | D34: Letsitele | E34: Small town | F34: spinach | G34: 23 | H34: 25 | I34: Male | J34: 18-30 | K34: Registered | L34: Yes | M34: Yes | N34: Owned | O34: Yes | P34: LRAD | Q34: 450997 | R34: 6.3 | S34: 4 | T34: 12.9 | U34: Yes | V34: Yes | W34: 149 | X34: 9 | Y34: Yes | Z34: 19.2 | AA34: 11.31 | AB34: 41.09375 | AC34: 0 | AD34: No Loan | AE34: 0 | AF34: Woolworths TNC | AG34: Yes | AH34: 0 | AI34: 3 | AJ34: Yes | AK34: Eskom grid | AL34: 12 | AM34: Yes | AN34: Medium | AO34: 33.3 | AP34: 50.8 | AQ34: 11.4 | AR34: 61 | AS34: No
A35: SME0034 | B35: Kopano Blue | C35: Limpopo | D35: Levubu | E35: Peri-urban | F35: tomatoes | G35: 21 | H35: 100 | I35: Male | J35: 60+ | K35: Registered | L35: Yes | M35: Yes | N35: Owned | O35: Yes | P35: MAFISA | Q35: 89558 | R35: 1.8 | S35: 2 | T35: 19.3 | U35: Yes | V35: Yes | W35: 103 | X35: 6 | Y35: No | Z35: 12.04 | AA35: 5.64 | AB35: 53.156146 | AC35: 0 | AD35: No Loan | AE35: 0 | AF35: Fairtrade | AG35: Yes | AH35: 4 | AI35: 0 | AJ35: Yes | AK35: Eskom grid | AL35: 22 | AM35: Yes | AN35: High | AO35: 15.4 | AP35: 22.7 | AQ35: 36.2 | AR35: 77.5 | AS35: No
A36: SME0035 | B36: Siyabonga Boerdery | C36: Limpopo | D36: Levubu | E36: Peri-urban | F36: litchis | G36: 10 | H36: 118 | I36: Male | J36: 31-40 | K36: Registered | L36: Yes | M36: Yes | N36: Leased | O36: Yes | P36: MAFISA | Q36: 435630 | R36: 36.8 | S36: 4 | T36: 11.9 | U36: Yes | V36: Yes | W36: 275 | X36: 9 | Y36: No | Z36: 37.86 | AA36: 25.39 | AB36: 32.937137 | AC36: 200003 | AD36: Current | AE36: 0.012126574 | AF36: Fairtrade | AG36: Yes | AH36: 4 | AI36: 0 | AJ36: Yes | AK36: Eskom grid | AL36: 9 | AM36: Yes | AN36: Medium | AO36: 83.1 | AP36: 16.4 | AQ36: 46 | AR36: 89 | AS36: No
A37: SME0036 | B37: Tsebo Golden | C37: Limpopo | D37: Bela-Bela | E37: Peri-urban | F37: tomatoes | G37: 27 | H37: 106 | I37: Male | J37: 31-40 | K37: Registered | L37: No | M37: Yes | N37: Owned | O37: Yes | P37: LRAD | Q37: 79840 | R37: -2.8 | S37: 4 | T37: 15.4 | U37: Yes | V37: Yes | W37: 234 | X37: 12 | Y37: Yes | Z37: 9.09 | AA37: 4.11 | AB37: 54.785479 | AC37: 0 | AD37: No Loan | AE37: 0 | AF37: Unknown | AG37: No | AH37: 4 | AI37: 3 | AJ37: Yes | AK37: Eskom grid | AL37: 20 | AM37: Unknown | AN37: Low | AO37: 23.8 | AP37: 54.7 | AQ37: 33 | AR37: 43.8 | AS37: No
A38: SME0037 | B38: Tlhaga Blue | C38: Limpopo | D38: Letsitele | E38: Peri-urban | F38: avocados | G38: 17 | H38: 61 | I38: Female | J38: 60+ | K38: Registered | L38: Yes | M38: Yes | N38: Owned | O38: Yes | P38: DTIC | Q38: 345985 | R38: 27.2 | S38: 5 | T38: 13.3 | U38: Yes | V38: Yes | W38: 203 | X38: 8 | Y38: Yes | Z38: 6.63 | AA38: 4.41 | AB38: 33.484163 | AC38: 586353 | AD38: Settled | AE38: 0.25561619 | AF38: Woolworths TNC | AG38: Yes | AH38: 0 | AI38: 2 | AJ38: Yes | AK38: Solar | AL38: 0 | AM38: Unknown | AN38: High | AO38: 98.1 | AP38: 43.5 | AQ38: 13.2 | AR38: 48.1 | AS38: No
A39: SME0038 | B39: Kopano Ubuntu | C39: Limpopo | D39: Letsitele | E39: Rural | F39: mangoes | G39: 9 | H39: 19 | I39: Male | J39: 41-50 | K39: Registered | L39: Yes | M39: Yes | N39: Owned | O39: Yes | P39: MAFISA | Q39: 489385 | R39: -17.1 | S39: 3 | T39: 9.1 | U39: Yes | V39: Unknown | W39: 209 | X39: 10 | Y39: No | Z39: 21.08 | AA39: 15.59 | AB39: 26.043643 | AC39: 398019 | AD39: Settled | AE39: 0.038581805 | AF39: SIZA | AG39: Yes | AH39: 3 | AI39: 0 | AJ39: Yes | AK39: Generator | AL39: 4 | AM39: Yes | AN39: Low | AO39: 32.8 | AP39: 30.7 | AQ39: 25.1 | AR39: 83.1 | AS39: Yes
A40: SME0039 | B40: Tlhaga Red | C40: Limpopo | D40: Tzaneen | E40: Small town | F40: avocados | G40: 22 | H40: 96 | I40: Male | J40: 41-50 | K40: Informal | L40: Yes | M40: No | N40: Owned | O40: No | P40: DTIC | Q40: 473162 | R40: 20.8 | S40: 1 | T40: 7.1 | U40: Yes | V40: Yes | W40: 22 | X40: 5 | Y40: Yes | Z40: 36.36 | AA40: 18.05 | AB40: 50.357536 | AC40: 453796 | AD40: Settled | AE40: 0.026377093 | AF40: Fairtrade | AG40: Yes | AH40: 3 | AI40: 0 | AJ40: Yes | AK40: Solar | AL40: 0 | AM40: Yes | AN40: High | AO40: 65 | AP40: 27.5 | AQ40: 10.1 | AR40: 84.1 | AS40: No
A41: SME0040 | B41: Mupo Siyabonga | C41: Limpopo | D41: Levubu | E41: Rural | F41: citrus | G41: 5 | H41: 24 | I41: Male | J41: 31-40 | K41: Informal | L41: Yes | M41: No | N41: Owned | O41: No | P41: None | Q41: 313366 | R41: 39.8 | S41: 3 | T41: 15 | U41: Yes | V41: Yes | W41: 153 | X41: 7 | Y41: No | Z41: 33.76 | AA41: 24.34 | AB41: 27.902844 | AC41: 634957 | AD41: Current | AE41: 0.060019172 | AF41: Organic (CERES) | AG41: No | AH41: 1 | AI41: 3 | AJ41: Yes | AK41: Eskom grid | AL41: 13 | AM41: Yes | AN41: Medium | AO41: 61.2 | AP41: 16 | AQ41: 18.9 | AR41: 100 | AS41: No
A42: SME0041 | B42: Tshivhase Old | C42: Limpopo | D42: Tzaneen | E42: Peri-urban | F42: litchis | G42: 25 | H42: 31 | I42: Male | J42: 60+ | K42: Registered | L42: Yes | M42: Yes | N42: Leased | O42: Yes | P42: CASP | Q42: 145096 | R42: 11.1 | S42: 3 | T42: 7.5 | U42: Yes | V42: Yes | W42: 182 | X42: 11 | Y42: No | Z42: 38.99 | AA42: 17.55 | AB42: 54.988459 | AC42: 440673 | AD42: Current | AE42: 0.077894675 | AF42: Woolworths TNC | AG42: Yes | AH42: 1 | AI42: 1 | AJ42: Yes | AK42: Eskom grid | AL42: 18 | AM42: No | AN42: High | AO42: 84.3 | AP42: 49.5 | AQ42: 42.1 | AR42: 41.7 | AS42: Yes
A43: SME0042 | B43: Khula Rainbow | C43: Limpopo | D43: Bela-Bela | E43: Small town | F43: tomatoes | G43: 16 | H43: 46 | I43: Male | J43: 41-50 | K43: Registered | L43: No | M43: Yes | N43: Owned | O43: Yes | P43: Agri-BEE | Q43: 118258 | R43: 21.3 | S43: 2 | T43: 11.6 | U43: Yes | V43: Yes | W43: 78 | X43: 8 | Y43: No | Z43: 18.45 | AA43: 13.75 | AB43: 25.474255 | AC43: 318973 | AD43: Settled | AE43: 0.14619315 | AF43: Woolworths TNC | AG43: Yes | AH43: 3 | AI43: 0 | AJ43: Yes | AK43: Eskom grid | AL43: 15 | AM43: Unknown | AN43: High | AO43: 94.5 | AP43: 70.5 | AQ43: 23.8 | AR43: 97.8 | AS43: No
A44: SME0043 | B44: Tshivhase Red | C44: Limpopo | D44: Letsitele | E44: Small town | F44: citrus | G44: 17 | H44: 73 | I44: Male | J44: 31-40 | K44: Registered | L44: No | M44: Yes | N44: Owned | O44: Yes | P44: DTIC | Q44: 265018 | R44: -17.1 | S44: 3 | T44: 12.4 | U44: Yes | V44: Yes | W44: 245 | X44: 7 | Y44: Yes | Z44: 39.04 | AA44: 20.39 | AB44: 47.771516 | AC44: 0 | AD44: No Loan | AE44: 0 | AF44: Woolworths TNC | AG44: No | AH44: 2 | AI44: 0 | AJ44: Yes | AK44: Generator | AL44: 2 | AM44: Yes | AN44: High | AO44: 7.4 | AP44: 45.3 | AQ44: 39.4 | AR44: 56.8 | AS44: No
... A50: SME0049 | B50: Tshivhase Morning | C50: Limpopo | D50: Levubu | E50: Peri-urban | F50: litchis | G50: 21 | H50: 52 | I50: Male | J50: 60+ | K50: Registered | L50: No | M50: Yes | N50: Owned | O50: No | P50: LRAD | Q50: 194886 | R50: 37.4 | S50: 4 | T50: 7.3 | U50: Yes | V50: Yes | W50: 217 | X50: 11 | Y50: No | Z50: 35.54 | AA50: 23.84 | AB50: 32.920653 | AC50: 0 | AD50: No Loan | AE50: 0 | AF50: Woolworths TNC | AG50: No | AH50: 4 | AI50: 0 | AJ50: Yes | AK50: Solar | AL50: 0 | AM50: No | AN50: Low | AO50: 91.7 | AP50: 17.9 | AQ50: 42.3 | AR50: 94.2 | AS50: Yes
A51: SME0050 | B51: Morning Laan | C51: Limpopo | D51: Levubu | E51: Peri-urban | F51: tomatoes | G51: 26 | H51: 22 | I51: Male | J51: 31-40 | K51: Registered | L51: Yes | M51: Yes | N51: Owned | O51: Yes | P51: DTIC | Q51: 297802 | S51: 1 | T51: 13.4 | U51: Yes | V51: Yes | W51: 16 | X51: 9 | Y51: Yes | Z51: 6.12 | AA51: 2.68 | AB51: 56.20915 | AC51: 338958 | AD51: Settled | AE51: 0.18598026 | AF51: Organic (CERES) | AG51: No | AH51: 0 | AI51: 3 | AJ51: Yes | AK51: Eskom grid | AL51: 12 | AM51: No | AN51: High | AO51: 37.4 | AP51: 72.4 | AQ51: 25.2 | AR51: 95 | AS51: No
A52: SME0051 | B52: Amandla New | C52: Mpumalanga | D52: Hazyview | E52: Rural | F52: citrus | G52: 25 | H52: 6 | I52: Male | J52: 51-60 | K52: Informal | L52: Yes | M52: Yes | N52: Owned | O52: No | P52: None | Q52: 114253 | S52: 5 | T52: 24.5 | U52: Yes | V52: No | W52: 84 | X52: 3 | Y52: Yes | Z52: 40.13 | AA52: 26.33 | AB52: 34.388238 | AC52: 528158 | AD52: Current | AE52: 0.11519327 | AF52: Fairtrade | AG52: Yes | AH52: 4 | AI52: 0 | AJ52: Yes | AK52: Generator | AL52: 2 | AM52: Yes | AN52: High | AO52: 23.4 | AP52: 25.2 | AQ52: 43.9 | AR52: 43.4 | AS52: No
A53: SME0052 | B53: Khula Silver | C53: Mpumalanga | D53: Hazyview | E53: Peri-urban | F53: avocados | G53: 2 | H53: 40 | I53: Male | J53: 51-60 | K53: Informal | L53: No | M53: Yes | N53: Owned | O53: Yes | P53: DTIC | Q53: 84962 | R53: -17.2 | S53: 3 | T53: 38.5 | U53: No | V53: No | W53: 273 | X53: 3 | Y53: No | Z53: 21.92 | AA53: 10.3 | AB53: 53.010949 | AC53: 430343 | AD53: Current | AE53: 0.23107314 | AF53: Unknown | AG53: No | AH53: 3 | AI53: 0 | AJ53: Yes | AK53: Solar | AL53: 0 | AM53: Yes | AN53: Medium | AO53: 38.8 | AP53: 27.8 | AQ53: 19.9 | AR53: 44.7 | AS53: No
A54: SME0053 | B54: Golden Green | C54: Mpumalanga | D54: Nelspruit | E54: Peri-urban | F54: tomatoes | G54: 16 | H54: 18 | I54: Male | J54: 41-50 | K54: Informal | L54: No | M54: No | N54: Leased | O54: Yes | P54: CASP | Q54: 47762 | R54: 36.2 | S54: 1 | T54: 33.7 | U54: No | V54: No | W54: 129 | X54: 6 | Y54: No | Z54: 13.98 | AA54: 10.01 | AB54: 28.397711 | AC54: 620411 | AD54: Settled | AE54: 0.92915852 | AF54: Organic (CERES) | AG54: No | AH54: 2 | AI54: 3 | AJ54: No | AK54: Generator | AL54: 3 | AM54: No | AN54: High | AO54: 91.4 | AP54: 35.9 | AQ54: 23.6 | AR54: 73.8 | AS54: Yes
A55: SME0054 | B55: Siyabonga Boerdery | C55: Mpumalanga | D55: Lydenburg | E55: Rural | F55: tomatoes | G55: 9 | H55: 36 | I55: Male | J55: 51-60 | K55: Registered | L55: Yes | M55: Yes | N55: Owned | O55: Yes | P55: LRAD | Q55: 116045 | R55: 27.7 | S55: 2 | T55: 18.5 | U55: Yes | V55: Yes | W55: 35 | X55: 5 | Y55: Yes | Z55: 39.02 | AA55: 28.41 | AB55: 27.191184 | AC55: 0 | AD55: No Loan | AE55: 0 | AF55: No Certificate | AG55: No | AH55: 1 | AI55: 0 | AJ55: Yes | AK55: Eskom grid | AL55: 8 | AM55: Unknown | AN55: Low | AO55: 61.8 | AP55: 56.7 | AQ55: 32.7 | AR55: 69 | AS55: No
A56: SME0055 | B56: Blue Plaas | C56: Mpumalanga | D56: Nelspruit | E56: Small town | F56: tomatoes | G56: 4 | H56: 11 | I56: Male | J56: 31-40 | K56: Registered | L56: Yes | M56: No | N56: Leased | O56: No | P56: LRAD | Q56: 101235 | R56: 11.6 | S56: 3 | T56: 21.7 | U56: Yes | V56: Yes | W56: 212 | X56: 4 | Y56: No | Z56: 44.62 | AA56: 19.65 | AB56: 55.961452 | AC56: 0 | AD56: No Loan | AE56: 0 | AF56: No Certificate | AG56: No | AH56: 0 | AI56: 0 | AJ56: Yes | AK56: Generator | AL56: 8 | AM56: No | AN56: Low | AO56: 70.3 | AP56: 15.8 | AQ56: 43 | AR56: 78.7 | AS56: Yes
A57: SME0056 | B57: Ubuntu Ridge | C57: Mpumalanga | D57: White River | E57: Peri-urban | F57: subtropical fruit | G57: 6 | H57: 25 | I57: Female | J57: 31-40 | K57: Registered | L57: Yes | M57: No | N57: Owned | O57: No | P57: DTIC | Q57: 38899 | R57: 25.1 | S57: 4 | T57: 38.2 | U57: Yes | V57: No | W57: 204 | X57: 6 | Y57: No | Z57: 18.94 | AA57: 12.35 | AB57: 34.794087 | AC57: 790782 | AD57: Settled | AE57: 1.0733426 | AF57: No Certificate | AG57: No | AH57: 0 | AI57: 3 | AJ57: Yes | AK57: Eskom grid | AL57: 21 | AM57: Unknown | AN57: High | AO57: 96.9 | AP57: 32.8 | AQ57: 33.5 | AR57: 87 | AS57: No
A58: SME0057 | B58: Sunrise Fields | C58: Mpumalanga | D58: Lydenburg | E58: Rural | F58: subtropical fruit | G58: 23 | H58: 9 | I58: Female | J58: 41-50 | K58: Informal | L58: No | M58: Yes | N58: Leased | O58: No | P58: LRAD | Q58: 69807 | S58: 2 | T58: 33.5 | U58: Yes | V58: Yes | W58: 7 | X58: 3 | Y58: Yes | Z58: 35.69 | AA58: 13.95 | AB58: 60.913421 | AC58: 344784 | AD58: Settled | AE58: 0.138389 | AF58: Woolworths TNC | AG58: Yes | AH58: 2 | AI58: 0 | AJ58: Yes | AK58: Solar | AL58: 0 | AM58: Yes | AN58: High | AO58: 1.2 | AP58: 39 | AQ58: 40.1 | AR58: 83.5 | AS58: No
A59: SME0058 | B59: Tlhaga New | C59: Mpumalanga | D59: Lydenburg | E59: Rural | F59: avocados | G59: 14 | H59: 24 | I59: Male | J59: 18-30 | K59: Registered | L59: Yes | M59: Yes | N59: Owned | O59: Unknown | P59: MAFISA | Q59: 52990 | R59: 36.7 | S59: 4 | T59: 29.8 | U59: Yes | V59: Yes | W59: 248 | X59: 1 | Y59: No | Z59: 18.96 | AA59: 11.34 | AB59: 40.189873 | AC59: 0 | AD59: No Loan | AE59: 0 | AF59: No Certificate | AG59: Yes | AH59: 4 | AI59: 1 | AJ59: Yes | AK59: Eskom grid | AL59: 13 | AM59: No | AN59: High | AO59: 31.4 | AP59: 77.5 | AQ59: 48.6 | AR59: 57.5 | AS59: No
A60: SME0059 | B60: Red Plaas | C60: Mpumalanga | D60: Lydenburg | E60: Peri-urban | F60: tomatoes | G60: 22 | H60: 40 | I60: Female | J60: 51-60 | K60: Registered | L60: No | M60: Yes | N60: Leased | O60: No | P60: None | Q60: 47479 | R60: 6.3 | S60: 3 | T60: 35.8 | U60: Yes | V60: No | W60: 214 | X60: 6 | Y60: No | Z60: 30.7 | AA60: 13.72 | AB60: 55.309446 | AC60: 0 | AD60: No Loan | AE60: 0 | AF60: No Certificate | AG60: No | AH60: 0 | AI60: 3 | AJ60: Yes | AK60: Solar | AL60: 0 | AM60: Yes | AN60: High | AO60: 54.4 | AP60: 65.4 | AQ60: 21.2 | AR60: 93.7 | AS60: No
A61: SME0060 | B61: Andile Laan | C61: Mpumalanga | D61: Hazyview | E61: Small town | F61: avocados | G61: 26 | H61: 32 | I61: Female | J61: 18-30 | K61: Registered | L61: No | M61: Yes | N61: Communal | O61: No | P61: CASP | Q61: 53913 | R61: -6.7 | S61: 5 | T61: 28.9 | U61: No | V61: No | W61: 118 | X61: 4 | Y61: Yes | Z61: 24.06 | AA61: 14.96 | AB61: 37.822111 | AC61: 0 | AD61: No Loan | AE61: 0 | AF61: SIZA | AG61: No | AH61: 3 | AI61: 0 | AJ61: No | AK61: Eskom grid | AL61: 14 | AM61: Yes | AN61: Medium | AO61: 34.8 | AP61: 34 | AQ61: 40.3 | AR61: 71.3 | AS61: Yes
A62: SME0061 | B62: Siyanda Thando | C62: Mpumalanga | D62: Lydenburg | E62: Rural | F62: tomatoes | G62: 22 | H62: 15 | I62: Male | J62: 60+ | K62: Registered | L62: No | M62: Yes | N62: Owned | O62: No | P62: LRAD | Q62: 92339 | R62: -10.4 | S62: 5 | T62: 25.7 | U62: Yes | V62: No | W62: 99 | X62: 2 | Y62: No | Z62: 22.85 | AA62: 8.26 | AB62: 63.851204 | AC62: 157860 | AD62: Current | AE62: 0.074817075 | AF62: GlobalG.A.P. | AG62: No | AH62: 2 | AI62: 0 | AJ62: Yes | AK62: Solar | AL62: 0 | AM62: No | AN62: Unknown | AO62: 36.6 | AP62: 23.8 | AQ62: 10.1 | AR62: 80.2 | AS62: No
A63: SME0062 | B63: Kopano Themba | C63: Mpumalanga | D63: Nelspruit | E63: Peri-urban | F63: tomatoes | G63: 20 | H63: 10 | I63: Male | J63: 41-50 | K63: Informal | L63: No | M63: No | N63: Communal | O63: No | P63: CASP | Q63: 51270 | R63: -1.7 | S63: 2 | T63: 24.3 | U63: Yes | V63: Yes | W63: 75 | X63: 5 | Y63: Yes | Z63: 13.24 | AA63: 8 | AB63: 39.577039 | AC63: 0 | AD63: No Loan | AE63: 0 | AF63: Organic (CERES) | AG63: No | AH63: 4 | AI63: 1 | AJ63: Yes | AK63: Generator | AL63: 6 | AM63: Yes | AN63: High | AO63: 61.9 | AP63: 70.6 | AQ63: 47.8 | AR63: 69.1 | AS63: Yes
A64: SME0063 | B64: New Plaas | C64: Mpumalanga | D64: Lydenburg | E64: Small town | F64: subtropical fruit | G64: 10 | H64: 7 | I64: Male | J64: 31-40 | K64: Informal | L64: Yes | M64: Yes | N64: Leased | O64: Yes | P64: DTIC | Q64: 57836 | R64: -9.9 | S64: 4 | T64: 29.1 | U64: No | V64: No | W64: 258 | X64: 5 | Y64: No | Z64: 28.34 | AA64: 12.96 | AB64: 54.269584 | AC64: 792715 | AD64: Unknown | AE64: 0.4836364 | AF64: No Certificate | AG64: No | AH64: 1 | AI64: 3 | AJ64: No | AK64: Eskom grid | AL64: 19 | AM64: No | AN64: High | AO64: 87.5 | AP64: 12.3 | AQ64: 16.8 | AR64: 91.7 | AS64: Yes
A65: SME0064 | B65: Thando Hoek | C65: Mpumalanga | D65: Hazyview | E65: Rural | F65: subtropical fruit | G65: 18 | H65: 22 | I65: Male | J65: 41-50 | K65: Registered | L65: No | M65: No | N65: Communal | O65: No | P65: None | Q65: 58356 | R65: -2.6 | S65: 3 | T65: 38.8 | U65: Yes | V65: No | W65: 53 | X65: 2 | Y65: No | Z65: 36.64 | AA65: 26.29 | AB65: 28.247817 | AC65: 0 | AD65: Unknown | AE65: 0 | AF65: No Certificate | AG65: Yes | AH65: 1 | AI65: 1 | AJ65: Yes | AK65: Eskom grid | AL65: 19 | AM65: Yes | AN65: High | AO65: 48.9 | AP65: 50.4 | AQ65: 17.1 | AR65: 64.9 | AS65: No
A66: SME0065 | B66: Amandla Sunrise | C66: Mpumalanga | D66: Hazyview | E66: Peri-urban | F66: tomatoes | G66: 24 | H66: 34 | I66: Male | J66: 18-30 | K66: Informal | L66: Yes | M66: Yes | N66: Owned | O66: No | P66: DTIC | Q66: 72129 | R66: -6.9 | S66: 4 | T66: 35.6 | U66: Yes | V66: Yes | W66: 150 | X66: 3 | Y66: No | Z66: 11.09 | AA66: 7.66 | AB66: 30.928765 | AC66: 0 | AD66: No Loan | AE66: 0 | AF66: No Certificate | AG66: No | AH66: 0 | AI66: 0 | AJ66: Yes | AK66: Generator | AL66: 2 | AM66: No | AN66: High | AO66: 45.7 | AP66: 79.4 | AQ66: 24.3 | AR66: 99.7 | AS66: No
A67: SME0066 | B67: Silver Ridge | C67: Mpumalanga | D67: Nelspruit | E67: Peri-urban | F67: tomatoes | G67: 24 | H67: 19 | I67: Male | J67: 18-30 | K67: Registered | L67: No | M67: Yes | N67: Owned | O67: Yes | P67: None | Q67: 32475 | R67: -19.9 | S67: 4 | T67: 16.9 | U67: Yes | V67: No | W67: 232 | X67: 1 | Y67: Yes | Z67: 19.4 | AA67: 7.73 | AB67: 60.154639 | AC67: 0 | AD67: No Loan | AE67: 0 | AF67: No Certificate | AG67: No | AH67: 1 | AI67: 3 | AJ67: No | AK67: Eskom grid | AL67: 19 | AM67: Yes | AN67: High | AO67: 88.1 | AP67: 19.6 | AQ67: 39.8 | AR67: 85.2 | AS67: Yes
A68: SME0067 | B68: New Fontein | C68: Mpumalanga | D68: Nelspruit | E68: Peri-urban | F68: avocados | G68: 28 | H68: 18 | I68: Female | J68: 18-30 | K68: Registered | L68: Yes | M68: No | N68: State land | O68: No | P68: LRAD | Q68: 118624 | R68: -12.6 | S68: 4 | T68: 23.8 | U68: Yes | V68: No | W68: 131 | X68: 3 | Y68: No | Z68: 15.68 | AA68: 9.26 | AB68: 40.943878 | AC68: 0 | AD68: No Loan | AE68: 0 | AF68: Fairtrade | AG68: No | AH68: 0 | AI68: 2 | AJ68: Yes | AK68: Eskom grid | AL68: 16 | AM68: Yes | AN68: High | AO68: 29.6 | AP68: 13.8 | AQ68: 45.4 | AR68: 97.3 | AS68: No
A69: SME0068 | B69: Green Laan | C69: Mpumalanga | D69: Nelspruit | E69: Peri-urban | F69: citrus | G69: 18 | H69: 16 | I69: Male | J69: 18-30 | K69: Informal | L69: Yes | M69: No | N69: Communal | O69: Unknown | P69: CASP | Q69: 96986 | R69: -15.9 | S69: 3 | T69: 20.4 | U69: No | V69: No | W69: 219 | X69: 5 | Y69: Yes | Z69: 33.79 | AA69: 22.19 | AB69: 34.329683 | AC69: 321822 | AD69: Settled | AE69: 0.098201583 | AF69: No Certificate | AG69: Yes | AH69: 2 | AI69: 0 | AJ69: No | AK69: Solar | AL69: 0 | AM69: No | AN69: Medium | AO69: 53.6 | AP69: 37.4 | AQ69: 33.5 | AR69: 90.1 | AS69: No
A70: SME0069 | B70: Old Farm | C70: Mpumalanga | D70: Lydenburg | E70: Rural | F70: avocados | G70: 10 | H70: 16 | I70: Female | J70: 18-30 | K70: Registered | L70: No | M70: Yes | N70: Owned | O70: No | P70: None | Q70: 37984 | R70: 22.1 | S70: 2 | T70: 27.4 | U70: Yes | V70: No | W70: 137 | X70: 2 | Y70: Yes | Z70: 35.24 | AA70: 24.65 | AB70: 30.051078 | AC70: 0 | AD70: No Loan | AE70: 0 | AF70: SIZA | AG70: No | AH70: 2 | AI70: 3 | AJ70: Yes | AK70: Eskom grid | AL70: 16 | AM70: No | AN70: Low | AO70: 49.6 | AP70: 45.8 | AQ70: 7.5 | AR70: 91.6 | AS70: Yes
... A72: SME0071 | B72: New Green | C72: KwaZulu-Natal | D72: Camperdown | E72: Rural | F72: green beans | G72: 1 | H72: 19 | I72: Male | J72: 18-30 | K72: Informal | L72: Yes | M72: No | N72: Owned | O72: Yes | P72: MAFISA | Q72: 20191 | R72: 25.5 | S72: 4 | T72: 36.2 | U72: No | V72: No | W72: 58 | X72: 2 | Y72: No | Z72: 15.29 | AA72: 8.36 | AB72: 45.323741 | AC72: 797567 | AD72: Current | AE72: 2.5834607 | AF72: GlobalG.A.P. | AG72: No | AH72: 4 | AI72: 3 | AJ72: No | AK72: Eskom grid | AL72: 15 | AM72: Yes | AN72: Low | AO72: 50.5 | AP72: 54.6 | AQ72: 22.7 | AR72: 75.5 | AS72: Yes
A73: SME0072 | B73: Lentswe New | C73: KwaZulu-Natal | D73: Camperdown | E73: Peri-urban | F73: butternut | G73: 7 | H73: 13 | I73: Female | J73: 31-40 | K73: Informal | L73: No | M73: Yes | N73: Owned | O73: Yes | P73: CASP | Q73: 41544 | S73: 3 | T73: 25.2 | U73: Yes | V73: No | W73: 111 | X73: 4 | Y73: Yes | Z73: 16.34 | AA73: 6.5 | AB73: 60.220318 | AC73: 548844 | AD73: Settled | AE73: 0.80851589 | AF73: Organic (CERES) | AG73: No | AH73: 2 | AI73: 1 | AJ73: Yes | AK73: Eskom grid | AL73: 19 | AM73: Yes | AN73: Low | AO73: 67.7 | AP73: 28.2 | AQ73: 49.6 | AR73: 41.9 | AS73: No
A74: SME0073 | B74: Siyanda Themba | C74: KwaZulu-Natal | D74: Greytown | E74: Rural | F74: bananas | G74: 27 | H74: 30 | I74: Male | J74: 18-30 | K74: Registered | L74: Yes | M74: No | N74: Leased | O74: Yes | P74: DTIC | Q74: 96823 | R74: -4.5 | S74: 1 | T74: 15.5 | U74: Yes | V74: Unknown | W74: 232 | X74: 2 | Y74: Yes | Z74: 39.04 | AA74: 26.3 | AB74: 32.633197 | AC74: 753825 | AD74: Defaulted | AE74: 0.19942619 | AF74: No Certificate | AG74: No | AH74: 0 | AI74: 3 | AJ74: Yes | AK74: Generator | AL74: 4 | AM74: No | AN74: High | AO74: 28 | AP74: 71.8 | AQ74: 6.6 | AR74: 77.2 | AS74: Yes
A75: SME0074 | B75: Thando Green | C75: KwaZulu-Natal | D75: Greytown | E75: Rural | F75: bananas | G75: 21 | H75: 39 | I75: Female | J75: 51-60 | K75: Registered | L75: Yes | M75: Yes | N75: Leased | O75: No | P75: None | Q75: 67069 | R75: 8.8 | S75: 4 | T75: 23.6 | U75: No | V75: Yes | W75: 143 | X75: 2 | Y75: Yes | Z75: 29.29 | AA75: 10.59 | AB75: 63.844315 | AC75: 0 | AD75: No Loan | AE75: 0 | AF75: Fairtrade | AG75: No | AH75: 3 | AI75: 2 | AJ75: No | AK75: Solar | AL75: 0 | AM75: No | AN75: Low | AO75: 24.8 | AP75: 26.9 | AQ75: 29 | AR75: 87.5 | AS75: No
A76: SME0075 | B76: Tlhaga Red | C76: KwaZulu-Natal | D76: Bergville | E76: Rural | F76: avocados | G76: 23 | H76: 27 | I76: Male | J76: 60+ | K76: Registered | L76: No | M76: Yes | N76: Owned | O76: Unknown | P76: LRAD | Q76: 129667 | R76: 39.3 | S76: 4 | T76: 28.6 | U76: Yes | V76: Yes | W76: 33 | X76: 2 | Y76: No | Z76: 6.78 | AA76: 3.67 | AB76: 45.870206 | AC76: 491308 | AD76: Current | AE76: 0.55884926 | AF76: No Certificate | AG76: No | AH76: 2 | AI76: 0 | AJ76: Yes | AK76: Eskom grid | AL76: 10 | AM76: No | AN76: Low | AO76: 84.6 | AP76: 70.2 | AQ76: 48.2 | AR76: 62.4 | AS76: No
A77: SME0076 | B77: Khula Rainbow | C77: KwaZulu-Natal | D77: Camperdown | E77: Rural | F77: butternut | G77: 21 | H77: 25 | I77: Male | J77: 60+ | K77: Informal | L77: No | M77: Yes | N77: State land | O77: No | P77: None | Q77: 136601 | R77: 35.7 | S77: 3 | T77: 20.6 | U77: Yes | V77: Yes | W77: 162 | X77: 6 | Y77: No | Z77: 10.97 | AA77: 7.04 | AB77: 35.824977 | AC77: 0 | AD77: No Loan | AE77: 0 | AF77: No Certificate | AG77: No | AH77: 4 | AI77: 0 | AJ77: Yes | AK77: Eskom grid | AL77: 17 | AM77: No | AN77: Medium | AO77: 64 | AP77: 17.3 | AQ77: 27.3 | AR77: 59.9 | AS77: Yes
A78: SME0077 | B78: Rainbow Hoek | C78: KwaZulu-Natal | D78: Midlands | E78: Peri-urban | F78: butternut | G78: 24 | H78: 5 | I78: Female | J78: 51-60 | K78: Registered | L78: Yes | M78: Yes | N78: Owned | O78: Unknown | P78: Agri-BEE | Q78: 116021 | R78: 5.2 | S78: 2 | T78: 37.1 | U78: Yes | V78: Yes | W78: 197 | X78: 1 | Y78: No | Z78: 36.76 | AA78: 21.37 | AB78: 41.866159 | AC78: 0 | AD78: In Arrears | AE78: 0 | AF78: Fairtrade | AG78: No | AH78: 0 | AI78: 2 | AJ78: Yes | AK78: Eskom grid | AL78: 13 | AM78: Yes | AN78: High | AO78: 17 | AP78: 36.3 | AQ78: 37.9 | AR78: 72.8 | AS78: No
A79: SME0078 | B79: Thando Plaas | C79: KwaZulu-Natal | D79: Greytown | E79: Peri-urban | F79: bananas | G79: 11 | H79: 18 | I79: Male | J79: 51-60 | K79: Informal | L79: Yes | M79: No | N79: Owned | O79: Unknown | P79: None | Q79: 92628 | R79: 23.3 | S79: 5 | T79: 21.6 | U79: Yes | V79: Yes | W79: 30 | X79: 4 | Y79: No | Z79: 38.75 | AA79: 15.94 | AB79: 58.864516 | AC79: 342085 | AD79: Settled | AE79: 0.095305955 | AF79: Organic (CERES) | AG79: No | AH79: 0 | AI79: 0 | AJ79: Yes | AK79: Eskom grid | AL79: 10 | AM79: Unknown | AN79: High | AO79: 84.4 | AP79: 31.6 | AQ79: 22.9 | AR79: 69.3 | AS79: No
A80: SME0079 | B80: Andile Plaas | C80: KwaZulu-Natal | D80: Camperdown | E80: Peri-urban | F80: green beans | G80: 19 | H80: 8 | I80: Male | J80: 18-30 | K80: Registered | L80: Yes | M80: Yes | N80: Owned | O80: Yes | P80: CASP | Q80: 107574 | R80: 0.6 | S80: 5 | T80: 25.3 | U80: No | V80: Unknown | W80: 121 | X80: 5 | Y80: Yes | Z80: 21.1 | AA80: 11.8 | AB80: 44.075829 | AC80: 0 | AD80: No Loan | AE80: 0 | AF80: No Certificate | AG80: No | AH80: 4 | AI80: 1 | AJ80: Yes | AK80: Generator | AL80: 6 | AM80: No | AN80: Low | AO80: 50.2 | AP80: 73 | AQ80: 41 | AR80: 80.7 | AS80: No
A81: SME0080 | B81: Thando Farm | C81: KwaZulu-Natal | D81: Bergville | E81: Rural | F81: avocados | G81: 27 | H81: 21 | I81: Male | J81: 18-30 | K81: Registered | L81: Yes | M81: No | N81: Leased | O81: Yes | P81: CASP | Q81: 70868 | R81: 13.4 | S81: 5 | T81: 23.2 | U81: Yes | V81: No | W81: 11 | X81: 6 | Y81: No | Z81: 26.38 | AA81: 13.66 | AB81: 48.218347 | AC81: 118560 | AD81: Current | AE81: 0.063418099 | AF81: No Certificate | AG81: No | AH81: 0 | AI81: 2 | AJ81: No | AK81: Solar | AL81: 0 | AM81: No | AN81: High | AO81: 38.3 | AP81: 44 | AQ81: 32.4 | AR81: 42.2 | AS81: Yes
A82: SME0081 | B82: Blue Fresh | C82: KwaZulu-Natal | D82: Greytown | E82: Small town | F82: butternut | G82: 11 | H82: 24 | I82: Male | J82: 41-50 | K82: Registered | L82: No | M82: No | N82: Owned | O82: No | P82: Agri-BEE | Q82: 132490 | R82: 21.8 | S82: 1 | T82: 39.3 | U82: Yes | V82: Yes | W82: 231 | X82: 3 | Y82: Yes | Z82: 22.25 | AA82: 13.53 | AB82: 39.191011 | AC82: 169112 | AD82: Settled | AE82: 0.057366891 | AF82: Checkers Good Farming | AG82: No | AH82: 2 | AI82: 0 | AJ82: No | AK82: Solar | AL82: 30 | AM82: Yes | AN82: High | AO82: 13.6 | AP82: 69.6 | AQ82: 44.6 | AR82: 41.7 | AS82: Yes
A83: SME0082 | B83: Vhembe Green | C83: KwaZulu-Natal | D83: Midlands | E83: Rural | F83: green beans | G83: 21 | H83: 12 | I83: Female | J83: 31-40 | K83: Informal | L83: No | M83: Yes | N83: State land | O83: No | P83: MAFISA | Q83: 84066 | S83: 2 | T83: 39 | U83: Yes | V83: No | W83: 181 | X83: 2 | Y83: No | Z83: 16.09 | AA83: 10.98 | AB83: 31.758856 | AC83: 21960 | AD83: In Arrears | AE83: 0.016235135 | AF83: No Certificate | AG83: No | AH83: 1 | AI83: 2 | AJ83: Yes | AK83: Generator | AL83: 10 | AM83: No | AN83: Low | AO83: 47.4 | AP83: 19.3 | AQ83: 12.8 | AR83: 88.1 | AS83: Yes
A84: SME0083 | B84: Siyanda Siyabonga | C84: KwaZulu-Natal | D84: Greytown | E84: Peri-urban | F84: green beans | G84: 19 | H84: 11 | I84: Female | J84: 60+ | K84: Registered | L84: Yes | M84: Yes | N84: State land | O84: No | P84: None | Q84: 146679 | R84: 30.6 | S84: 3 | T84: 29 | U84: Yes | V84: Yes | W84: 60 | X84: 4 | Y84: Yes | Z84: 44.55 | AA84: 27.01 | AB84: 39.371493 | AC84: 0 | AD84: No Loan | AE84: 0 | AF84: Fairtrade | AG84: No | AH84: 2 | AI84: 1 | AJ84: No | AK84: Eskom grid | AL84: 16 | AM84: No | AN84: High | AO84: 66.1 | AP84: 57.7 | AQ84: 37.5 | AR84: 79.3 | AS84: No
A85: SME0084 | B85: Mupo Silver | C85: KwaZulu-Natal | D85: Greytown | E85: Small town | F85: bananas | G85: 22 | H85: 39 | I85: Male | J85: 41-50 | K85: Informal | L85: No | M85: Yes | N85: Leased | O85: No | P85: DTIC | Q85: 59347 | R85: 30.7 | S85: 5 | T85: 19.5 | U85: Yes | V85: Yes | W85: 137 | X85: 6 | Y85: No | Z85: 35.75 | AA85: 15.13 | AB85: 57.678322 | AC85: 0 | AD85: No Loan | AE85: 0 | AF85: Woolworths TNC | AG85: Yes | AH85: 2 | AI85: 1 | AJ85: No | AK85: Eskom grid | AL85: 14 | AM85: Yes | AN85: High | AO85: 58.6 | AP85: 42.5 | AQ85: 10.3 | AR85: 43.2 | AS85: No
A86: SME0085 | B86: Rainbow Hoek | C86: KwaZulu-Natal | D86: Bergville | E86: Small town | F86: bananas | G86: 7 | H86: 26 | I86: Male | J86: 60+ | K86: Registered | L86: Yes | M86: Yes | N86: Leased | O86: No | P86: Agri-BEE | Q86: 38772 | R86: -1 | S86: 2 | T86: 34.5 | U86: Yes | V86: No | W86: 95 | X86: 3 | Y86: No | Z86: 6.18 | AA86: 2.84 | AB86: 54.045307 | AC86: 0 | AD86: No Loan | AE86: 0 | AF86: SIZA | AG86: No | AH86: 3 | AI86: 0 | AJ86: Yes | AK86: Eskom grid | AL86: 17 | AM86: Yes | AN86: High | AO86: 96.5 | AP86: 36.8 | AQ86: 6.7 | AR86: 52 | AS86: No
A87: SME0086 | B87: Thando Laan | C87: KwaZulu-Natal | D87: Bergville | E87: Small town | F87: bananas | G87: 5 | H87: 11 | I87: Male | J87: 60+ | K87: Registered | L87: No | M87: Yes | N87: Communal | O87: No | P87: DTIC | Q87: 60123 | R87: -10 | S87: 1 | T87: 22.5 | U87: Yes | V87: No | W87: 273 | X87: 3 | Y87: Yes | Z87: 32.78 | AA87: 13.23 | AB87: 59.640024 | AC87: 0 | AD87: No Loan | AE87: 0 | AF87: Checkers Good Farming | AG87: No | AH87: 1 | AI87: 3 | AJ87: Yes | AK87: Eskom grid | AL87: 11 | AM87: Unknown | AN87: Medium | AO87: 73.4 | AP87: 51.3 | AQ87: 12.6 | AR87: 62 | AS87: No
A88: SME0087 | B88: Tshivhase Themba | C88: KwaZulu-Natal | D88: Camperdown | E88: Small town | F88: bananas | G88: 14 | H88: 33 | I88: Male | J88: 18-30 | K88: Informal | L88: No | M88: Yes | N88: Owned | O88: Yes | P88: DTIC | Q88: 53126 | R88: 8.5 | S88: 2 | T88: 20.1 | U88: No | V88: Yes | W88: 9 | X88: 3 | Y88: Yes | Z88: 9.94 | AA88: 5.55 | AB88: 44.16499 | AC88: 560581 | AD88: Current | AE88: 1.0615608 | AF88: Checkers Good Farming | AG88: No | AH88: 2 | AI88: 0 | AJ88: Yes | AK88: Eskom grid | AL88: 15 | AM88: Yes | AN88: High | AO88: 83.1 | AP88: 78.1 | AQ88: 21.1 | AR88: 64.6 | AS88: Yes
A89: SME0088 | B89: Kopano Themba | C89: KwaZulu-Natal | D89: Greytown | E89: Rural | F89: butternut | G89: 5 | I89: Female | J89: 18-30 | K89: Registered | L89: No | M89: No | N89: State land | O89: No | P89: MAFISA | Q89: 104454 | R89: -6.1 | S89: 3 | T89: 21.6 | U89: Yes | V89: No | W89: 25 | X89: 3 | Y89: Yes | Z89: 32.39 | AA89: 16.86 | AB89: 47.946897 | AC89: 680997 | AD89: Current | AE89: 0.20128396 | AF89: No Certificate | AG89: No | AH89: 1 | AI89: 2 | AJ89: Yes | AK89: Eskom grid | AL89: 22 | AM89: No | AN89: Low | AO89: 37.3 | AP89: 34 | AQ89: 10.1 | AR89: 64 | AS89: No
A90: SME0089 | B90: Blue Farm | C90: KwaZulu-Natal | D90: Bergville | E90: Rural | F90: bananas | G90: 19 | H90: 35 | I90: Male | J90: 31-40 | K90: Informal | L90: Yes | M90: No | N90: Owned | O90: Yes | P90: DTIC | Q90: 69774 | R90: 26.7 | S90: 5 | T90: 15.7 | U90: No | V90: Unknown | W90: 71 | X90: 4 | Y90: No | Z90: 10.4 | AA90: 5.35 | AB90: 48.557692 | AC90: 209290 | AD90: Settled | AE90: 0.28841744 | AF90: No Certificate | AG90: No | AH90: 4 | AI90: 1 | AJ90: Yes | AK90: Eskom grid | AL90: 16 | AM90: No | AN90: Low | AP90: 60.9 | AQ90: 26.7 | AR90: 79.8 | AS90: No
A91: SME0090 | B91: New Fontein | C91: KwaZulu-Natal | D91: Bergville | E91: Peri-urban | F91: green beans | G91: 2 | H91: 37 | I91: Male | J91: 60+ | K91: Registered | L91: Yes | M91: Yes | N91: Owned | O91: Yes | P91: None | Q91: 69628 | R91: 4.2 | S91: 2 | T91: 17 | U91: Yes | V91: Unknown | W91: 50 | X91: 4 | Y91: Yes | Z91: 10.63 | AA91: 5.84 | AB91: 45.061148 | AC91: 0 | AD91: No Loan | AE91: 0 | AF91: Unknown | AG91: No | AH91: 4 | AI91: 0 | AJ91: Yes | AK91: Eskom grid | AL91: 20 | AM91: No | AN91: High | AO91: 89 | AP91: 49.4 | AQ91: 34.5 | AR91: 67.4 | AS91: Yes
A92: SME0091 | B92: Lentswe Golden | C92: Gauteng | D92: Sedibeng | E92: Peri-urban | F92: baby vegetables | G92: 25 | H92: 19 | I92: Female | J92: 41-50 | K92: Registered | L92: No | M92: Yes | N92: Owned | O92: Yes | P92: MAFISA | Q92: 128774 | R92: 18 | S92: 3 | T92: 28.7 | U92: Yes | V92: Yes | W92: 89 | X92: 4 | Y92: Yes | Z92: 33.96 | AA92: 21.69 | AB92: 36.130742 | AC92: 488681 | AD92: Defaulted | AE92: 0.11174538 | AF92: SIZA | AG92: No | AH92: 1 | AI92: 2 | AJ92: Yes | AK92: Eskom grid | AL92: 20 | AM92: No | AN92: Low | AO92: 77.2 | AP92: 41.5 | AQ92: 34.6 | AR92: 97.4 | AS92: Yes
A93: SME0092 | B93: Rainbow Fields | C93: Gauteng | D93: Westonaria | E93: Peri-urban | F93: herbs | G93: 24 | H93: 13 | I93: Female | J93: N/A | K93: Registered | L93: Yes | M93: No | N93: Leased | O93: Yes | P93: None | Q93: 98714 | R93: 16.4 | S93: 3 | T93: 27.6 | U93: Yes | V93: No | W93: 132 | X93: 3 | Y93: Yes | Z93: 19.37 | AA93: 9.06 | AB93: 53.226639 | AC93: 0 | AD93: No Loan | AE93: 0 | AF93: SIZA | AG93: No | AH93: 4 | AI93: 2 | AJ93: No | AK93: Eskom grid | AL93: 19 | AM93: No | AN93: Medium | AO93: 20.1 | AP93: 53.7 | AQ93: 18.1 | AR93: 60.7 | AS93: No
A94: SME0093 | B94: Siyanda Blue | C94: Gauteng | D94: Tshwane peri-urban | E94: Peri-urban | F94: cabbage | G94: 28 | H94: 32 | I94: Female | J94: 60+ | K94: Registered | L94: No | M94: Yes | N94: Owned | O94: Yes | P94: CASP | Q94: 23312 | R94: 2.9 | S94: 1 | T94: 31.8 | U94: Yes | V94: Unknown | W94: 87 | X94: 3 | Y94: No | Z94: 11.71 | AA94: 4.39 | AB94: 62.510675 | AC94: 0 | AD94: No Loan | AE94: 0 | AF94: SIZA | AG94: No | AH94: 2 | AI94: 3 | AJ94: No | AK94: Eskom grid | AL94: 17 | AM94: No | AN94: Medium | AO94: 74.2 | AP94: 49.3 | AQ94: 15.7 | AR94: 87.1 | AS94: No
A95: SME0094 | B95: Sunrise Ridge | C95: Gauteng | D95: Sedibeng | E95: Peri-urban | F95: bananas | G95: 27 | H95: 19 | I95: Male | J95: 60+ | K95: Registered | L95: No | M95: Yes | N95: Owned | O95: Yes | P95: DTIC | Q95: 116790 | R95: 16.2 | S95: 2 | T95: 22.4 | U95: Yes | V95: No | W95: 100 | X95: 2 | Y95: No | Z95: 10.65 | AA95: 3.9 | AB95: 63.380282 | AC95: 211392 | AD95: Defaulted | AE95: 0.16995474 | AF95: GlobalG.A.P. | AG95: No | AH95: 1 | AI95: 0 | AJ95: Yes | AK95: Eskom grid | AL95: 22 | AM95: Yes | AN95: High | AO95: 49.1 | AP95: 50.1 | AQ95: 21.1 | AR95: 87 | AS95: Yes
A96: SME0095 | B96: Izifundo Silver | C96: Gauteng | D96: Tshwane peri-urban | E96: Peri-urban | F96: baby vegetables | G96: 22 | H96: 26 | I96: Male | J96: 41-50 | K96: Registered | L96: Yes | M96: Yes | N96: Leased | O96: Yes | P96: MAFISA | Q96: 48632 | R96: 37 | S96: 5 | T96: 28.3 | U96: No | V96: Unknown | W96: 9 | X96: 1 | Y96: No | Z96: 23.38 | AA96: 16.64 | AB96: 28.828058 | AC96: 496905 | AD96: Settled | AE96: 0.43702545 | AF96: No Certificate | AG96: No | AH96: 0 | AI96: 3 | AJ96: No | AK96: Eskom grid | AL96: 16 | AM96: Yes | AN96: High | AO96: 51.4 | AP96: 45.6 | AQ96: 26.9 | AR96: 57.8 | AS96: No
A97: SME0096 | B97: Ubuntu Hoek | C97: Gauteng | D97: Tshwane peri-urban | E97: Peri-urban | F97: baby vegetables | G97: 27 | H97: 11 | I97: Male | J97: 60+ | K97: Registered | L97: Yes | M97: Yes | N97: State land | O97: No | P97: None | Q97: 135164 | R97: 38.6 | S97: 4 | T97: 31.2 | U97: No | V97: Unknown | W97: 83 | X97: 1 | Y97: No | Z97: 18.94 | AA97: 7.29 | AB97: 61.510032 | AC97: 635372 | AD97: Settled | AE97: 0.24819159 | AF97: No Certificate | AG97: No | AH97: 3 | AI97: 3 | AJ97: Yes | AK97: Generator | AL97: 8 | AM97: Yes | AN97: Low | AO97: 53.5 | AP97: 54.9 | AQ97: 32.8 | AR97: 85.4 | AS97: No
A98: SME0097 | B98: Tshivhase Morning | C98: Gauteng | D98: Tshwane peri-urban | E98: Peri-urban | F98: cabbage | G98: 27 | H98: 6 | I98: Male | J98: 31-40 | K98: Registered | L98: Yes | M98: No | N98: Owned | O98: Yes | P98: DTIC | Q98: 48818 | R98: -11.8 | S98: 4 | U98: No | V98: No | W98: 156 | X98: 6 | Y98: Yes | Z98: 32.41 | AA98: 23.19 | AB98: 28.44801 | AC98: 0 | AD98: No Loan | AE98: 0 | AF98: Unknown | AG98: No | AH98: 0 | AI98: 1 | AJ98: Yes | AK98: Eskom grid | AL98: 8 | AM98: No | AN98: Low | AO98: 30.5 | AP98: 62.4 | AQ98: 45.7 | AR98: 60.6 | AS98: No
A99: SME0098 | B99: Amandla Morning | C99: Gauteng | D99: Tshwane peri-urban | E99: Peri-urban | F99: citrus | G99: 28 | H99: 40 | I99: Male | J99: 60+ | K99: Informal | L99: Yes | M99: Yes | N99: Owned | O99: No | P99: CASP | Q99: 58096 | R99: 20.3 | S99: 3 | T99: 17.5 | U99: No | V99: No | W99: 254 | X99: 3 | Y99: Yes | Z99: 32.18 | AA99: 14.28 | AB99: 55.624612 | AC99: 55847 | AD99: Defaulted | AE99: 0.029872225 | AF99: Unknown | AG99: No | AH99: 2 | AI99: 1 | AJ99: Yes | AK99: Eskom grid | AL99: 20 | AM99: Yes | AN99: Low | AO99: 31.3 | AP99: 65 | AQ99: 37 | AR99: 78.5 | AS99: Yes
A100: SME0099 | B100: Sunrise Ridge | C100: Gauteng | D100: Sedibeng | E100: Peri-urban | F100: herbs | G100: 7 | H100: 22 | I100: Male | J100: 60+ | K100: Registered | L100: Yes | M100: Yes | N100: Owned | O100: Yes | P100: LRAD | Q100: 54502 | R100: 24 | S100: 1 | T100: 33.2 | U100: No | V100: Unknown | W100: 264 | X100: 6 | Y100: Yes | Z100: 28.69 | AA100: 14.69 | AB100: 48.79749 | AC100: 725043 | AD100: Settled | AE100: 0.46368258 | AF100: No Certificate | AG100: No | AH100: 1 | AI100: 2 | AJ100: No | AK100: Generator | AL100: 5 | AM100: No | AN100: High | AO100: 13.4 | AP100: 45.1 | AQ100: 9.1 | AR100: 61.8 | AS100: Yes
A101: SME0100 | B101: Thando Green | C101: Gauteng | D101: Tshwane peri-urban | E101: Peri-urban | F101: herbs | G101: 12 | H101: 7 | I101: Male | J101: 51-60 | K101: Registered | L101: No | M101: Yes | N101: State land | O101: No | P101: LRAD | Q101: 28239 | R101: -4.1 | S101: 2 | T101: 16.1 | U101: Yes | V101: No | W101: 189 | X101: 4 | Y101: No | Z101: 23.73 | AA101: 8.75 | AB101: 63.126844 | AC101: 0 | AD101: No Loan | AE101: 0 | AF101: Fairtrade | AG101: No | AH101: 4 | AI101: 2 | AJ101: Yes | AK101: Eskom grid | AL101: 17 | AM101: Yes | AN101: High | AO101: 36.5 | AP101: 55.7 | AQ101: 42.6 | AR101: 71 | AS101: No
A102: SME0101 | B102: Khula Silver | C102: Gauteng | D102: Sedibeng | E102: Peri-urban | F102: herbs | G102: 3 | H102: 37 | I102: Male | J102: 31-40 | K102: Informal | L102: Yes | M102: No | N102: Leased | O102: Yes | P102: LRAD | Q102: 44498 | S102: 5 | T102: 32.9 | U102: Yes | V102: Yes | W102: 174 | X102: 6 | Y102: Yes | Z102: 32.33 | AA102: 17.51 | AB102: 45.839777 | AC102: 517807 | AD102: Current | AE102: 0.35993305 | AF102: GlobalG.A.P. | AG102: No | AH102: 1 | AI102: 1 | AJ102: Yes | AK102: Eskom grid | AL102: 22 | AM102: Yes | AN102: High | AO102: 92.2 | AP102: 46.2 | AQ102: 23.2 | AR102: 98.2 | AS102: No
A103: SME0102 | B103: Tlhaga Siyabonga | C103: Gauteng | D103: Sedibeng | E103: Peri-urban | F103: baby vegetables | G103: 20 | H103: 37 | I103: Male | J103: 31-40 | K103: Informal | L103: Yes | M103: No | N103: Leased | O103: No | P103: None | Q103: 109861 | R103: 0.6 | S103: 4 | T103: 29.9 | U103: Yes | V103: Unknown | W103: 72 | X103: 1 | Y103: Yes | Z103: 26.39 | AA103: 18.84 | AB103: 28.609322 | AC103: 0 | AD103: No Loan | AE103: 0 | AF103: No Certificate | AG103: No | AH103: 1 | AI103: 3 | AJ103: No | AK103: Eskom grid | AL103: 22 | AM103: No | AN103: Low | AO103: 9.3 | AP103: 56.2 | AQ103: 45.6 | AR103: 72.4 | AS103: Yes
A104: SME0103 | B104: Ubuntu Ridge | C104: Gauteng | D104: Tshwane peri-urban | E104: Peri-urban | F104: baby vegetables | G104: 14 | H104: 13 | I104: Male | J104: 51-60 | K104: Registered | L104: No | M104: No | N104: Owned | O104: Yes | P104: LRAD | Q104: 139286 | R104: 31.5 | S104: 3 | T104: 30 | U104: No | V104: Yes | W104: 7 | X104: 6 | Y104: No | Z104: 6.28 | AA104: 3.51 | AB104: 44.10828 | AC104: 300024 | AD104: Current | AE104: 0.34299587 | AF104: Woolworths TNC | AG104: Yes | AH104: 3 | AI104: 2 | AJ104: Yes | AK104: Eskom grid | AL104: 21 | AM104: No | AN104: High | AO104: 99.2 | AP104: 37.8 | AQ104: 14.2 | AR104: 73.1 | AS104: No
A105: SME0104 | B105: Sunrise Laan | C105: Gauteng | D105: Westonaria | E105: Peri-urban | F105: herbs | G105: 28 | H105: 12 | I105: Male | J105: 51-60 | K105: Informal | L105: No | M105: No | N105: Leased | O105: Yes | P105: None | Q105: 144419 | R105: -10.3 | S105: 2 | T105: 27.7 | U105: No | V105: No | W105: 31 | X105: 2 | Y105: Yes | Z105: 30.8 | AA105: 20.69 | AB105: 32.824675 | AC105: 0 | AD105: No Loan | AE105: 0 | AF105: Checkers Good Farming | AG105: No | AH105: 0 | AI105: 0 | AJ105: Yes | AK105: Eskom grid | AL105: 11 | AM105: No | AN105: High | AO105: 93.1 | AP105: 38 | AQ105: 34.5 | AR105: 57.2 | AS105: No
A106: SME0105 | B106: Vhembe Silver | C106: Gauteng | D106: Sedibeng | E106: Peri-urban | F106: herbs | G106: 26 | H106: 37 | I106: Male | J106: 60+ | K106: Registered | L106: No | M106: No | N106: Owned | O106: Yes | P106: LRAD | Q106: 108345 | R106: -17.8 | S106: 2 | T106: 31.4 | U106: No | V106: No | W106: 49 | X106: 3 | Y106: No | Z106: 19.77 | AA106: 10.04 | AB106: 49.215984 | AC106: 414194 | AD106: Current | AE106: 0.19336963 | AF106: Unknown | AG106: No | AH106: 4 | AI106: 2 | AJ106: Yes | AK106: Eskom grid | AL106: 21 | AM106: No | AN106: Medium | AO106: 45.5 | AP106: 38.3 | AQ106: 5.2 | AR106: 50.5 | AS106: No
A107: SME0106 | B107: Khula Sunrise | C107: North West | D107: Moretele | E107: Small town | F107: tomatoes | G107: 13 | H107: 35 | I107: Male | J107: Unknown | K107: Informal | L107: No | M107: No | N107: State land | O107: No | P107: Agri-BEE | Q107: 109337 | R107: 7.6 | S107: 5 | T107: 36.6 | U107: Yes | V107: Yes | W107: 200 | X107: 6 | Y107: No | Z107: 14.59 | AA107: 9.2 | AB107: 36.943112 | AC107: 0 | AD107: No Loan | AE107: 0 | AF107: Woolworths TNC | AG107: No | AH107: 4 | AI107: 0 | AJ107: Yes | AK107: Eskom grid | AL107: 11 | AM107: Yes | AN107: High | AO107: 7.6 | AP107: 75.2 | AQ107: 26.4 | AR107: 61.2 | AS107: No
A108: SME0107 | B108: Andile Farm | C108: North West | D108: Moretele | E108: Rural | F108: onions | G108: 27 | H108: 27 | I108: Male | J108: 18-30 | K108: Informal | L108: No | M108: Yes | N108: Leased | O108: Yes | P108: CASP | Q108: 140610 | R108: -15.3 | S108: 4 | T108: 30.3 | U108: No | V108: No | W108: 26 | X108: 4 | Y108: Yes | Z108: 18.3 | AA108: 12.98 | AB108: 29.071038 | AC108: 0 | AD108: No Loan | AE108: 0 | AF108: Unknown | AG108: No | AH108: 1 | AI108: 2 | AJ108: No | AK108: Generator | AL108: 5 | AM108: Unknown | AN108: High | AO108: 47.8 | AP108: 47.9 | AQ108: 27.6 | AR108: 63.6 | AS108: No
...

Sheet Score_Calculations
A1: sme_id | B1: sme_name | C1: business_registration_status | D1: financial_statements_prepared | E1: separate_bank_account | F1: title_deed | G1: land_ownership_type | H1: years_in_operation | I1: previous_grant_or_investment | J1: num_employees | K1: annual_production_volume_kg | L1: post_harvest_loss_pct | M1: storage_access | N1: cold_chain_capacity | O1: production_diversity_count | P1: gross_margin_pct | Q1: num_buyers | R1: formal_offtake_contracts | S1: certification_status | T1: export_readiness | U1: loan_repayment_status | V1: debt_to_revenue_ratio | W1: irrigation_present | X1: energy_mitigation_present | Y1: electricity_source | Z1: loadshedding_days_per_month | AA1: drought_events_5yr | AB1: pct_women_leadership | AC1: pct_women_workforce | AD1: pct_youth_employees | AE1: pct_hdi_employees | AF1: sources_from_women_farmers
A2: SME0001 | B2: Thando Boerdery | C2: =IF(cleaned_data!K2="Registered",1,0) -> 1 | D2: =IF(cleaned_data!L2="Yes",1,0) -> 1 | E2: =IF(cleaned_data!M2="Yes",1,0) -> 1 | F2: =IF(cleaned_data!O2="Unknown","",IF(cleaned_data!O2="Yes",1,0)) | G2: {=_xlfn.IFS(cleaned_data!N2="Owned",1,cleaned_data!N2="Leased",0.75,cleaned_data!N2="State land",0.5,cleaned_data!N2="Communal",0.25)} -> 1 | H2: {=_xlfn.IFS(cleaned_data!G2>=10,1,cleaned_data!G2>=5,0.75,cleaned_data!G2>=2,0.5,TRUE,0.25)} -> 1 | I2: =IF(cleaned_data!P2="None",0,1) -> 1 | J2: {=_xlfn.IFS(cleaned_data!H2>=20,1,cleaned_data!H2>=10,0.75,cleaned_data!H2>=5,0.5,cleaned_data!H2>=1,0.25,TRUE,0)} -> 1 | K2: {=_xlfn.IFS(cleaned_data!Q2>=100000,1,cleaned_data!Q2>=50000,0.75,cleaned_data!Q2>=10000,0.5,TRUE,0.25)} -> 1 | L2: {=_xlfn.IFS(cleaned_data!T2="","",cleaned_data!T2<=10,1,cleaned_data!T2<=25,0.75,cleaned_data!T2<=40,0.5, cleaned_data!T2>40,0.25)} -> 1 | M2: =IF(cleaned_data!U2="Yes",1,0) -> 1 | N2: {=_xlfn.IFS(cleaned_data!V2="Unknown","",cleaned_data!V2="Yes",1,TRUE,0)} -> 1 | O2: {=_xlfn.IFS(cleaned_data!S2>=4,1,cleaned_data!S2=3,0.75,cleaned_data!S2=2,0.5,cleaned_data!S2=1,0.25,TRUE,0)} -> 1 | P2: {=_xlfn.IFS(cleaned_data!AB2>=50,1,cleaned_data!AB2>=35,0.75,cleaned_data!AB2>=20,0.5,TRUE,0.25)} -> 0.5 | Q2: {=_xlfn.IFS(cleaned_data!X2>=5,1,cleaned_data!X2>=3,0.75,cleaned_data!X2=2,0.5,cleaned_data!X2=1,0.25,TRUE,0)} -> 1 | R2: =IF(cleaned_data!Y2="Yes",1,0) -> 1 | S2: =IF(OR(cleaned_data!AF2="GlobalG.A.P.",cleaned_data!AF2="Fairtrade",cleaned_data!AF2="Organic (CERES)"),1, IF(OR(cleaned_data!AF2="SIZA",cleaned_data!AF2="Woolworths TNC",cleaned_data!AF2="Checkers Good Farming"),0.75, IF(cleaned_data!AF2="No Certificate",0, IF(cleaned_data!AF2="Unknown","","")))) -> 1 | T2: =IF(cleaned_data!AG2="Yes",1,0) -> 1 | U2: =IF(OR(cleaned_data!AD2="No Loan",cleaned_data!AD2="Settled",cleaned_data!AD2="Current"),1, IF(cleaned_data!AD2="In Arrears",0.5, IF(cleaned_data!AD2="Defaulted",0, IF(cleaned_data!AD2="Unknown","","")))) -> 1 | V2: {=_xlfn.IFS(cleaned_data!AE2<=0.2,1, cleaned_data!AE2<=0.5,0.75, cleaned_data!AE2<=1,0.5, cleaned_data!AE2>1,0.25)} -> 1 | W2: =IF(cleaned_data!AJ2="Yes",1,0) -> 1 | X2: {=_xlfn.IFS(cleaned_data!AM2="Yes", 1, cleaned_data!AM2="No", 0, cleaned_data!AM2="Unknown", "")} -> 1 | Y2: {=_xlfn.IFS(cleaned_data!AK2="Solar", 1, cleaned_data!AK2="Generator", 0.75, cleaned_data!AK2="Eskom grid", 0.5, TRUE, "")} -> 0.5 | Z2: {=_xlfn.IFS(cleaned_data!AL2="", "", cleaned_data!AL2<=8, 1, cleaned_data!AL2<=14, 0.75, cleaned_data!AL2<=21, 0.5, cleaned_data!AL2>=22, 0.25)} -> 0.5 | AA2: {=_xlfn.IFS(cleaned_data!AH2=0, 1, cleaned_data!AH2=1, 0.75, cleaned_data!AH2=2, 0.5, cleaned_data!AH2>=3, 0.25)} -> 0.5 | AB2: {=_xlfn.IFS(cleaned_data!AO2="", "", cleaned_data!AO2>=50, 1, cleaned_data!AO2>=30, 0.75, cleaned_data!AO2>=10, 0.5, cleaned_data!AO2<10, 0.25)} -> 0.75 | AC2: {=_xlfn.IFS(cleaned_data!AP2>=50,1, cleaned_data!AP2>=30,0.75, cleaned_data!AP2>=10,0.5, cleaned_data!AP2<10,0.25)} -> 0.75 | AD2: {=_xlfn.IFS(cleaned_data!AQ2>=30,1, cleaned_data!AQ2>=20,0.75, cleaned_data!AQ2>=10,0.5, cleaned_data!AQ2<10,0.25)} -> 0.5 | AE2: {=_xlfn.IFS(cleaned_data!AR2>=75,1, cleaned_data!AR2>=50,0.75, cleaned_data!AR2>=25,0.5, cleaned_data!AR2<25,0.25)} -> 0.5 | AF2: =IF(cleaned_data!AS2="Yes",1,0) -> 0
A3: SME0002 | B3: Tlhaga Morning | C3: =IF(cleaned_data!K3="Registered",1,0) -> 1 | D3: =IF(cleaned_data!L3="Yes",1,0) -> 1 | E3: =IF(cleaned_data!M3="Yes",1,0) -> 1 | F3: =IF(cleaned_data!O3="Unknown","",IF(cleaned_data!O3="Yes",1,0)) -> 1 | G3: {=_xlfn.IFS(cleaned_data!N3="Owned",1,cleaned_data!N3="Leased",0.75,cleaned_data!N3="State land",0.5,cleaned_data!N3="Communal",0.25)} -> 1 | H3: {=_xlfn.IFS(cleaned_data!G3>=10,1,cleaned_data!G3>=5,0.75,cleaned_data!G3>=2,0.5,TRUE,0.25)} -> 0.5 | I3: =IF(cleaned_data!P3="None",0,1) -> 1 | J3: {=_xlfn.IFS(cleaned_data!H3>=20,1,cleaned_data!H3>=10,0.75,cleaned_data!H3>=5,0.5,cleaned_data!H3>=1,0.25,TRUE,0)} -> 1 | K3: {=_xlfn.IFS(cleaned_data!Q3>=100000,1,cleaned_data!Q3>=50000,0.75,cleaned_data!Q3>=10000,0.5,TRUE,0.25)} -> 1 | L3: {=_xlfn.IFS(cleaned_data!T3="","",cleaned_data!T3<=10,1,cleaned_data!T3<=25,0.75,cleaned_data!T3<=40,0.5, cleaned_data!T3>40,0.25)} -> 1 | M3: =IF(cleaned_data!U3="Yes",1,0) -> 1 | N3: {=_xlfn.IFS(cleaned_data!V3="Unknown","",cleaned_data!V3="Yes",1,TRUE,0)} -> 1 | O3: {=_xlfn.IFS(cleaned_data!S3>=4,1,cleaned_data!S3=3,0.75,cleaned_data!S3=2,0.5,cleaned_data!S3=1,0.25,TRUE,0)} -> 0.75 | P3: {=_xlfn.IFS(cleaned_data!AB3>=50,1,cleaned_data!AB3>=35,0.75,cleaned_data!AB3>=20,0.5,TRUE,0.25)} -> 1 | Q3: {=_xlfn.IFS(cleaned_data!X3>=5,1,cleaned_data!X3>=3,0.75,cleaned_data!X3=2,0.5,cleaned_data!X3=1,0.25,TRUE,0)} -> 1 | R3: =IF(cleaned_data!Y3="Yes",1,0) -> 1 | S3: =IF(OR(cleaned_data!AF3="GlobalG.A.P.",cleaned_data!AF3="Fairtrade",cleaned_data!AF3="Organic (CERES)"),1, IF(OR(cleaned_data!AF3="SIZA",cleaned_data!AF3="Woolworths TNC",cleaned_data!AF3="Checkers Good Farming"),0.75, IF(cleaned_data!AF3="No Certificate",0, IF(cleaned_data!AF3="Unknown","","")))) | T3: =IF(cleaned_data!AG3="Yes",1,0) -> 0 | U3: =IF(OR(cleaned_data!AD3="No Loan",cleaned_data!AD3="Settled",cleaned_data!AD3="Current"),1, IF(cleaned_data!AD3="In Arrears",0.5, IF(cleaned_data!AD3="Defaulted",0, IF(cleaned_data!AD3="Unknown","","")))) -> 1 | V3: {=_xlfn.IFS(cleaned_data!AE3<=0.2,1, cleaned_data!AE3<=0.5,0.75, cleaned_data!AE3<=1,0.5, cleaned_data!AE3>1,0.25)} -> 1 | W3: =IF(cleaned_data!AJ3="Yes",1,0) -> 1 | X3: {=_xlfn.IFS(cleaned_data!AM3="Yes", 1, cleaned_data!AM3="No", 0, cleaned_data!AM3="Unknown", "")} -> 1 | Y3: {=_xlfn.IFS(cleaned_data!AK3="Solar", 1, cleaned_data!AK3="Generator", 0.75, cleaned_data!AK3="Eskom grid", 0.5, TRUE, "")} -> 0.5 | Z3: {=_xlfn.IFS(cleaned_data!AL3="", "", cleaned_data!AL3<=8, 1, cleaned_data!AL3<=14, 0.75, cleaned_data!AL3<=21, 0.5, cleaned_data!AL3>=22, 0.25)} -> 0.5 | AA3: {=_xlfn.IFS(cleaned_data!AH3=0, 1, cleaned_data!AH3=1, 0.75, cleaned_data!AH3=2, 0.5, cleaned_data!AH3>=3, 0.25)} -> 1 | AB3: {=_xlfn.IFS(cleaned_data!AO3="", "", cleaned_data!AO3>=50, 1, cleaned_data!AO3>=30, 0.75, cleaned_data!AO3>=10, 0.5, cleaned_data!AO3<10, 0.25)} -> 1 | AC3: {=_xlfn.IFS(cleaned_data!AP3>=50,1, cleaned_data!AP3>=30,0.75, cleaned_data!AP3>=10,0.5, cleaned_data!AP3<10,0.25)} -> 0.75 | AD3: {=_xlfn.IFS(cleaned_data!AQ3>=30,1, cleaned_data!AQ3>=20,0.75, cleaned_data!AQ3>=10,0.5, cleaned_data!AQ3<10,0.25)} -> 1 | AE3: {=_xlfn.IFS(cleaned_data!AR3>=75,1, cleaned_data!AR3>=50,0.75, cleaned_data!AR3>=25,0.5, cleaned_data!AR3<25,0.25)} -> 0.75 | AF3: =IF(cleaned_data!AS3="Yes",1,0) -> 0
A4: SME0003 | B4: Vhembe Red | C4: =IF(cleaned_data!K4="Registered",1,0) -> 1 | D4: =IF(cleaned_data!L4="Yes",1,0) -> 1 | E4: =IF(cleaned_data!M4="Yes",1,0) -> 1 | F4: =IF(cleaned_data!O4="Unknown","",IF(cleaned_data!O4="Yes",1,0)) -> 0 | G4: {=_xlfn.IFS(cleaned_data!N4="Owned",1,cleaned_data!N4="Leased",0.75,cleaned_data!N4="State land",0.5,cleaned_data!N4="Communal",0.25)} -> 0.5 | H4: {=_xlfn.IFS(cleaned_data!G4>=10,1,cleaned_data!G4>=5,0.75,cleaned_data!G4>=2,0.5,TRUE,0.25)} -> 1 | I4: =IF(cleaned_data!P4="None",0,1) -> 1 | J4: {=_xlfn.IFS(cleaned_data!H4>=20,1,cleaned_data!H4>=10,0.75,cleaned_data!H4>=5,0.5,cleaned_data!H4>=1,0.25,TRUE,0)} -> 1 | K4: {=_xlfn.IFS(cleaned_data!Q4>=100000,1,cleaned_data!Q4>=50000,0.75,cleaned_data!Q4>=10000,0.5,TRUE,0.25)} -> 1 | L4: {=_xlfn.IFS(cleaned_data!T4="","",cleaned_data!T4<=10,1,cleaned_data!T4<=25,0.75,cleaned_data!T4<=40,0.5, cleaned_data!T4>40,0.25)} -> 1 | M4: =IF(cleaned_data!U4="Yes",1,0) -> 1 | N4: {=_xlfn.IFS(cleaned_data!V4="Unknown","",cleaned_data!V4="Yes",1,TRUE,0)} -> 1 | O4: {=_xlfn.IFS(cleaned_data!S4>=4,1,cleaned_data!S4=3,0.75,cleaned_data!S4=2,0.5,cleaned_data!S4=1,0.25,TRUE,0)} -> 0.25 | P4: {=_xlfn.IFS(cleaned_data!AB4>=50,1,cleaned_data!AB4>=35,0.75,cleaned_data!AB4>=20,0.5,TRUE,0.25)} -> 0.75 | Q4: {=_xlfn.IFS(cleaned_data!X4>=5,1,cleaned_data!X4>=3,0.75,cleaned_data!X4=2,0.5,cleaned_data!X4=1,0.25,TRUE,0)} -> 1 | R4: =IF(cleaned_data!Y4="Yes",1,0) -> 1 | S4: =IF(OR(cleaned_data!AF4="GlobalG.A.P.",cleaned_data!AF4="Fairtrade",cleaned_data!AF4="Organic (CERES)"),1, IF(OR(cleaned_data!AF4="SIZA",cleaned_data!AF4="Woolworths TNC",cleaned_data!AF4="Checkers Good Farming"),0.75, IF(cleaned_data!AF4="No Certificate",0, IF(cleaned_data!AF4="Unknown","","")))) -> 0.75 | T4: =IF(cleaned_data!AG4="Yes",1,0) -> 1 | U4: =IF(OR(cleaned_data!AD4="No Loan",cleaned_data!AD4="Settled",cleaned_data!AD4="Current"),1, IF(cleaned_data!AD4="In Arrears",0.5, IF(cleaned_data!AD4="Defaulted",0, IF(cleaned_data!AD4="Unknown","","")))) -> 1 | V4: {=_xlfn.IFS(cleaned_data!AE4<=0.2,1, cleaned_data!AE4<=0.5,0.75, cleaned_data!AE4<=1,0.5, cleaned_data!AE4>1,0.25)} -> 1 | W4: =IF(cleaned_data!AJ4="Yes",1,0) -> 1 | X4: {=_xlfn.IFS(cleaned_data!AM4="Yes", 1, cleaned_data!AM4="No", 0, cleaned_data!AM4="Unknown", "")} -> 1 | Y4: {=_xlfn.IFS(cleaned_data!AK4="Solar", 1, cleaned_data!AK4="Generator", 0.75, cleaned_data!AK4="Eskom grid", 0.5, TRUE, "")} -> 1 | Z4: {=_xlfn.IFS(cleaned_data!AL4="", "", cleaned_data!AL4<=8, 1, cleaned_data!AL4<=14, 0.75, cleaned_data!AL4<=21, 0.5, cleaned_data!AL4>=22, 0.25)} -> 1 | AA4: {=_xlfn.IFS(cleaned_data!AH4=0, 1, cleaned_data!AH4=1, 0.75, cleaned_data!AH4=2, 0.5, cleaned_data!AH4>=3, 0.25)} -> 1 | AB4: {=_xlfn.IFS(cleaned_data!AO4="", "", cleaned_data!AO4>=50, 1, cleaned_data!AO4>=30, 0.75, cleaned_data!AO4>=10, 0.5, cleaned_data!AO4<10, 0.25)} -> 0.25 | AC4: {=_xlfn.IFS(cleaned_data!AP4>=50,1, cleaned_data!AP4>=30,0.75, cleaned_data!AP4>=10,0.5, cleaned_data!AP4<10,0.25)} -> 1 | AD4: {=_xlfn.IFS(cleaned_data!AQ4>=30,1, cleaned_data!AQ4>=20,0.75, cleaned_data!AQ4>=10,0.5, cleaned_data!AQ4<10,0.25)} -> 1 | AE4: {=_xlfn.IFS(cleaned_data!AR4>=75,1, cleaned_data!AR4>=50,0.75, cleaned_data!AR4>=25,0.5, cleaned_data!AR4<25,0.25)} -> 1 | AF4: =IF(cleaned_data!AS4="Yes",1,0) -> 0
A5: SME0004 | B5: Tsebo Red | C5: =IF(cleaned_data!K5="Registered",1,0) -> 1 | D5: =IF(cleaned_data!L5="Yes",1,0) -> 1 | E5: =IF(cleaned_data!M5="Yes",1,0) -> 1 | F5: =IF(cleaned_data!O5="Unknown","",IF(cleaned_data!O5="Yes",1,0)) -> 1 | G5: {=_xlfn.IFS(cleaned_data!N5="Owned",1,cleaned_data!N5="Leased",0.75,cleaned_data!N5="State land",0.5,cleaned_data!N5="Communal",0.25)} -> 1 | H5: {=_xlfn.IFS(cleaned_data!G5>=10,1,cleaned_data!G5>=5,0.75,cleaned_data!G5>=2,0.5,TRUE,0.25)} -> 1 | I5: =IF(cleaned_data!P5="None",0,1) -> 1 | J5: {=_xlfn.IFS(cleaned_data!H5>=20,1,cleaned_data!H5>=10,0.75,cleaned_data!H5>=5,0.5,cleaned_data!H5>=1,0.25,TRUE,0)} -> 1 | K5: {=_xlfn.IFS(cleaned_data!Q5>=100000,1,cleaned_data!Q5>=50000,0.75,cleaned_data!Q5>=10000,0.5,TRUE,0.25)} -> 1 | L5: {=_xlfn.IFS(cleaned_data!T5="","",cleaned_data!T5<=10,1,cleaned_data!T5<=25,0.75,cleaned_data!T5<=40,0.5, cleaned_data!T5>40,0.25)} -> 1 | M5: =IF(cleaned_data!U5="Yes",1,0) -> 1 | N5: {=_xlfn.IFS(cleaned_data!V5="Unknown","",cleaned_data!V5="Yes",1,TRUE,0)} | O5: {=_xlfn.IFS(cleaned_data!S5>=4,1,cleaned_data!S5=3,0.75,cleaned_data!S5=2,0.5,cleaned_data!S5=1,0.25,TRUE,0)} -> 0.75 | P5: {=_xlfn.IFS(cleaned_data!AB5>=50,1,cleaned_data!AB5>=35,0.75,cleaned_data!AB5>=20,0.5,TRUE,0.25)} -> 0.5 | Q5: {=_xlfn.IFS(cleaned_data!X5>=5,1,cleaned_data!X5>=3,0.75,cleaned_data!X5=2,0.5,cleaned_data!X5=1,0.25,TRUE,0)} -> 0.75 | R5: =IF(cleaned_data!Y5="Yes",1,0) -> 1 | S5: =IF(OR(cleaned_data!AF5="GlobalG.A.P.",cleaned_data!AF5="Fairtrade",cleaned_data!AF5="Organic (CERES)"),1, IF(OR(cleaned_data!AF5="SIZA",cleaned_data!AF5="Woolworths TNC",cleaned_data!AF5="Checkers Good Farming"),0.75, IF(cleaned_data!AF5="No Certificate",0, IF(cleaned_data!AF5="Unknown","","")))) -> 1 | T5: =IF(cleaned_data!AG5="Yes",1,0) -> 1 | U5: =IF(OR(cleaned_data!AD5="No Loan",cleaned_data!AD5="Settled",cleaned_data!AD5="Current"),1, IF(cleaned_data!AD5="In Arrears",0.5, IF(cleaned_data!AD5="Defaulted",0, IF(cleaned_data!AD5="Unknown","","")))) -> 1 | V5: {=_xlfn.IFS(cleaned_data!AE5<=0.2,1, cleaned_data!AE5<=0.5,0.75, cleaned_data!AE5<=1,0.5, cleaned_data!AE5>1,0.25)} -> 1 | W5: =IF(cleaned_data!AJ5="Yes",1,0) -> 1 | X5: {=_xlfn.IFS(cleaned_data!AM5="Yes", 1, cleaned_data!AM5="No", 0, cleaned_data!AM5="Unknown", "")} -> 0 | Y5: {=_xlfn.IFS(cleaned_data!AK5="Solar", 1, cleaned_data!AK5="Generator", 0.75, cleaned_data!AK5="Eskom grid", 0.5, TRUE, "")} -> 0.5 | Z5: {=_xlfn.IFS(cleaned_data!AL5="", "", cleaned_data!AL5<=8, 1, cleaned_data!AL5<=14, 0.75, cleaned_data!AL5<=21, 0.5, cleaned_data!AL5>=22, 0.25)} -> 0.25 | AA5: {=_xlfn.IFS(cleaned_data!AH5=0, 1, cleaned_data!AH5=1, 0.75, cleaned_data!AH5=2, 0.5, cleaned_data!AH5>=3, 0.25)} -> 0.25 | AB5: {=_xlfn.IFS(cleaned_data!AO5="", "", cleaned_data!AO5>=50, 1, cleaned_data!AO5>=30, 0.75, cleaned_data!AO5>=10, 0.5, cleaned_data!AO5<10, 0.25)} -> 1 | AC5: {=_xlfn.IFS(cleaned_data!AP5>=50,1, cleaned_data!AP5>=30,0.75, cleaned_data!AP5>=10,0.5, cleaned_data!AP5<10,0.25)} -> 0.75 | AD5: {=_xlfn.IFS(cleaned_data!AQ5>=30,1, cleaned_data!AQ5>=20,0.75, cleaned_data!AQ5>=10,0.5, cleaned_data!AQ5<10,0.25)} -> 1 | AE5: {=_xlfn.IFS(cleaned_data!AR5>=75,1, cleaned_data!AR5>=50,0.75, cleaned_data!AR5>=25,0.5, cleaned_data!AR5<25,0.25)} -> 0.75 | AF5: =IF(cleaned_data!AS5="Yes",1,0) -> 0
A6: SME0005 | B6: Silver Valley | C6: =IF(cleaned_data!K6="Registered",1,0) -> 1 | D6: =IF(cleaned_data!L6="Yes",1,0) -> 1 | E6: =IF(cleaned_data!M6="Yes",1,0) -> 1 | F6: =IF(cleaned_data!O6="Unknown","",IF(cleaned_data!O6="Yes",1,0)) -> 1 | G6: {=_xlfn.IFS(cleaned_data!N6="Owned",1,cleaned_data!N6="Leased",0.75,cleaned_data!N6="State land",0.5,cleaned_data!N6="Communal",0.25)} -> 1 | H6: {=_xlfn.IFS(cleaned_data!G6>=10,1,cleaned_data!G6>=5,0.75,cleaned_data!G6>=2,0.5,TRUE,0.25)} -> 0.75 | I6: =IF(cleaned_data!P6="None",0,1) -> 1 | J6: {=_xlfn.IFS(cleaned_data!H6>=20,1,cleaned_data!H6>=10,0.75,cleaned_data!H6>=5,0.5,cleaned_data!H6>=1,0.25,TRUE,0)} -> 1 | K6: {=_xlfn.IFS(cleaned_data!Q6>=100000,1,cleaned_data!Q6>=50000,0.75,cleaned_data!Q6>=10000,0.5,TRUE,0.25)} -> 1 | L6: {=_xlfn.IFS(cleaned_data!T6="","",cleaned_data!T6<=10,1,cleaned_data!T6<=25,0.75,cleaned_data!T6<=40,0.5, cleaned_data!T6>40,0.25)} -> 1 | M6: =IF(cleaned_data!U6="Yes",1,0) -> 1 | N6: {=_xlfn.IFS(cleaned_data!V6="Unknown","",cleaned_data!V6="Yes",1,TRUE,0)} -> 0 | O6: {=_xlfn.IFS(cleaned_data!S6>=4,1,cleaned_data!S6=3,0.75,cleaned_data!S6=2,0.5,cleaned_data!S6=1,0.25,TRUE,0)} -> 1 | P6: {=_xlfn.IFS(cleaned_data!AB6>=50,1,cleaned_data!AB6>=35,0.75,cleaned_data!AB6>=20,0.5,TRUE,0.25)} -> 1 | Q6: {=_xlfn.IFS(cleaned_data!X6>=5,1,cleaned_data!X6>=3,0.75,cleaned_data!X6=2,0.5,cleaned_data!X6=1,0.25,TRUE,0)} -> 1 | R6: =IF(cleaned_data!Y6="Yes",1,0) -> 0 | S6: =IF(OR(cleaned_data!AF6="GlobalG.A.P.",cleaned_data!AF6="Fairtrade",cleaned_data!AF6="Organic (CERES)"),1, IF(OR(cleaned_data!AF6="SIZA",cleaned_data!AF6="Woolworths TNC",cleaned_data!AF6="Checkers Good Farming"),0.75, IF(cleaned_data!AF6="No Certificate",0, IF(cleaned_data!AF6="Unknown","","")))) -> 0.75 | T6: =IF(cleaned_data!AG6="Yes",1,0) -> 1 | U6: =IF(OR(cleaned_data!AD6="No Loan",cleaned_data!AD6="Settled",cleaned_data!AD6="Current"),1, IF(cleaned_data!AD6="In Arrears",0.5, IF(cleaned_data!AD6="Defaulted",0, IF(cleaned_data!AD6="Unknown","","")))) -> 1 | V6: {=_xlfn.IFS(cleaned_data!AE6<=0.2,1, cleaned_data!AE6<=0.5,0.75, cleaned_data!AE6<=1,0.5, cleaned_data!AE6>1,0.25)} -> 1 | W6: =IF(cleaned_data!AJ6="Yes",1,0) -> 1 | X6: {=_xlfn.IFS(cleaned_data!AM6="Yes", 1, cleaned_data!AM6="No", 0, cleaned_data!AM6="Unknown", "")} -> 0 | Y6: {=_xlfn.IFS(cleaned_data!AK6="Solar", 1, cleaned_data!AK6="Generator", 0.75, cleaned_data!AK6="Eskom grid", 0.5, TRUE, "")} -> 1 | Z6: {=_xlfn.IFS(cleaned_data!AL6="", "", cleaned_data!AL6<=8, 1, cleaned_data!AL6<=14, 0.75, cleaned_data!AL6<=21, 0.5, cleaned_data!AL6>=22, 0.25)} | AA6: {=_xlfn.IFS(cleaned_data!AH6=0, 1, cleaned_data!AH6=1, 0.75, cleaned_data!AH6=2, 0.5, cleaned_data!AH6>=3, 0.25)} -> 1 | AB6: {=_xlfn.IFS(cleaned_data!AO6="", "", cleaned_data!AO6>=50, 1, cleaned_data!AO6>=30, 0.75, cleaned_data!AO6>=10, 0.5, cleaned_data!AO6<10, 0.25)} -> 0.5 | AC6: {=_xlfn.IFS(cleaned_data!AP6>=50,1, cleaned_data!AP6>=30,0.75, cleaned_data!AP6>=10,0.5, cleaned_data!AP6<10,0.25)} -> 0.5 | AD6: {=_xlfn.IFS(cleaned_data!AQ6>=30,1, cleaned_data!AQ6>=20,0.75, cleaned_data!AQ6>=10,0.5, cleaned_data!AQ6<10,0.25)} -> 0.75 | AE6: {=_xlfn.IFS(cleaned_data!AR6>=75,1, cleaned_data!AR6>=50,0.75, cleaned_data!AR6>=25,0.5, cleaned_data!AR6<25,0.25)} -> 0.75 | AF6: =IF(cleaned_data!AS6="Yes",1,0) -> 1
A7: SME0006 | B7: Tshivhase Silver | C7: =IF(cleaned_data!K7="Registered",1,0) -> 0 | D7: =IF(cleaned_data!L7="Yes",1,0) -> 1 | E7: =IF(cleaned_data!M7="Yes",1,0) -> 0 | F7: =IF(cleaned_data!O7="Unknown","",IF(cleaned_data!O7="Yes",1,0)) -> 0 | G7: {=_xlfn.IFS(cleaned_data!N7="Owned",1,cleaned_data!N7="Leased",0.75,cleaned_data!N7="State land",0.5,cleaned_data!N7="Communal",0.25)} -> 0.75 | H7: {=_xlfn.IFS(cleaned_data!G7>=10,1,cleaned_data!G7>=5,0.75,cleaned_data!G7>=2,0.5,TRUE,0.25)} -> 0.75 | I7: =IF(cleaned_data!P7="None",0,1) -> 1 | J7: {=_xlfn.IFS(cleaned_data!H7>=20,1,cleaned_data!H7>=10,0.75,cleaned_data!H7>=5,0.5,cleaned_data!H7>=1,0.25,TRUE,0)} -> 1 | K7: {=_xlfn.IFS(cleaned_data!Q7>=100000,1,cleaned_data!Q7>=50000,0.75,cleaned_data!Q7>=10000,0.5,TRUE,0.25)} -> 1 | L7: {=_xlfn.IFS(cleaned_data!T7="","",cleaned_data!T7<=10,1,cleaned_data!T7<=25,0.75,cleaned_data!T7<=40,0.5, cleaned_data!T7>40,0.25)} -> 0.75 | M7: =IF(cleaned_data!U7="Yes",1,0) -> 0 | N7: {=_xlfn.IFS(cleaned_data!V7="Unknown","",cleaned_data!V7="Yes",1,TRUE,0)} -> 0 | O7: {=_xlfn.IFS(cleaned_data!S7>=4,1,cleaned_data!S7=3,0.75,cleaned_data!S7=2,0.5,cleaned_data!S7=1,0.25,TRUE,0)} -> 0.5 | P7: {=_xlfn.IFS(cleaned_data!AB7>=50,1,cleaned_data!AB7>=35,0.75,cleaned_data!AB7>=20,0.5,TRUE,0.25)} -> 0.75 | Q7: {=_xlfn.IFS(cleaned_data!X7>=5,1,cleaned_data!X7>=3,0.75,cleaned_data!X7=2,0.5,cleaned_data!X7=1,0.25,TRUE,0)} -> 1 | R7: =IF(cleaned_data!Y7="Yes",1,0) -> 1 | S7: =IF(OR(cleaned_data!AF7="GlobalG.A.P.",cleaned_data!AF7="Fairtrade",cleaned_data!AF7="Organic (CERES)"),1, IF(OR(cleaned_data!AF7="SIZA",cleaned_data!AF7="Woolworths TNC",cleaned_data!AF7="Checkers Good Farming"),0.75, IF(cleaned_data!AF7="No Certificate",0, IF(cleaned_data!AF7="Unknown","","")))) -> 0.75 | T7: =IF(cleaned_data!AG7="Yes",1,0) -> 1 | U7: =IF(OR(cleaned_data!AD7="No Loan",cleaned_data!AD7="Settled",cleaned_data!AD7="Current"),1, IF(cleaned_data!AD7="In Arrears",0.5, IF(cleaned_data!AD7="Defaulted",0, IF(cleaned_data!AD7="Unknown","","")))) -> 1 | V7: {=_xlfn.IFS(cleaned_data!AE7<=0.2,1, cleaned_data!AE7<=0.5,0.75, cleaned_data!AE7<=1,0.5, cleaned_data!AE7>1,0.25)} -> 1 | W7: =IF(cleaned_data!AJ7="Yes",1,0) -> 1 | X7: {=_xlfn.IFS(cleaned_data!AM7="Yes", 1, cleaned_data!AM7="No", 0, cleaned_data!AM7="Unknown", "")} -> 1 | Y7: {=_xlfn.IFS(cleaned_data!AK7="Solar", 1, cleaned_data!AK7="Generator", 0.75, cleaned_data!AK7="Eskom grid", 0.5, TRUE, "")} -> 0.5 | Z7: {=_xlfn.IFS(cleaned_data!AL7="", "", cleaned_data!AL7<=8, 1, cleaned_data!AL7<=14, 0.75, cleaned_data!AL7<=21, 0.5, cleaned_data!AL7>=22, 0.25)} -> 1 | AA7: {=_xlfn.IFS(cleaned_data!AH7=0, 1, cleaned_data!AH7=1, 0.75, cleaned_data!AH7=2, 0.5, cleaned_data!AH7>=3, 0.25)} -> 0.75 | AB7: {=_xlfn.IFS(cleaned_data!AO7="", "", cleaned_data!AO7>=50, 1, cleaned_data!AO7>=30, 0.75, cleaned_data!AO7>=10, 0.5, cleaned_data!AO7<10, 0.25)} -> 0.25 | AC7: {=_xlfn.IFS(cleaned_data!AP7>=50,1, cleaned_data!AP7>=30,0.75, cleaned_data!AP7>=10,0.5, cleaned_data!AP7<10,0.25)} -> 1 | AD7: {=_xlfn.IFS(cleaned_data!AQ7>=30,1, cleaned_data!AQ7>=20,0.75, cleaned_data!AQ7>=10,0.5, cleaned_data!AQ7<10,0.25)} -> 0.75 | AE7: {=_xlfn.IFS(cleaned_data!AR7>=75,1, cleaned_data!AR7>=50,0.75, cleaned_data!AR7>=25,0.5, cleaned_data!AR7<25,0.25)} -> 1 | AF7: =IF(cleaned_data!AS7="Yes",1,0) -> 1
A8: SME0007 | B8: Amandla Golden | C8: =IF(cleaned_data!K8="Registered",1,0) -> 1 | D8: =IF(cleaned_data!L8="Yes",1,0) -> 1 | E8: =IF(cleaned_data!M8="Yes",1,0) -> 1 | F8: =IF(cleaned_data!O8="Unknown","",IF(cleaned_data!O8="Yes",1,0)) | G8: {=_xlfn.IFS(cleaned_data!N8="Owned",1,cleaned_data!N8="Leased",0.75,cleaned_data!N8="State land",0.5,cleaned_data!N8="Communal",0.25)} -> 0.75 | H8: {=_xlfn.IFS(cleaned_data!G8>=10,1,cleaned_data!G8>=5,0.75,cleaned_data!G8>=2,0.5,TRUE,0.25)} -> 1 | I8: =IF(cleaned_data!P8="None",0,1) -> 1 | J8: {=_xlfn.IFS(cleaned_data!H8>=20,1,cleaned_data!H8>=10,0.75,cleaned_data!H8>=5,0.5,cleaned_data!H8>=1,0.25,TRUE,0)} -> 1 | K8: {=_xlfn.IFS(cleaned_data!Q8>=100000,1,cleaned_data!Q8>=50000,0.75,cleaned_data!Q8>=10000,0.5,TRUE,0.25)} -> 1 | L8: {=_xlfn.IFS(cleaned_data!T8="","",cleaned_data!T8<=10,1,cleaned_data!T8<=25,0.75,cleaned_data!T8<=40,0.5, cleaned_data!T8>40,0.25)} -> 0.75 | M8: =IF(cleaned_data!U8="Yes",1,0) -> 0 | N8: {=_xlfn.IFS(cleaned_data!V8="Unknown","",cleaned_data!V8="Yes",1,TRUE,0)} -> 0 | O8: {=_xlfn.IFS(cleaned_data!S8>=4,1,cleaned_data!S8=3,0.75,cleaned_data!S8=2,0.5,cleaned_data!S8=1,0.25,TRUE,0)} -> 1 | P8: {=_xlfn.IFS(cleaned_data!AB8>=50,1,cleaned_data!AB8>=35,0.75,cleaned_data!AB8>=20,0.5,TRUE,0.25)} -> 0.75 | Q8: {=_xlfn.IFS(cleaned_data!X8>=5,1,cleaned_data!X8>=3,0.75,cleaned_data!X8=2,0.5,cleaned_data!X8=1,0.25,TRUE,0)} -> 1 | R8: =IF(cleaned_data!Y8="Yes",1,0) -> 1 | S8: =IF(OR(cleaned_data!AF8="GlobalG.A.P.",cleaned_data!AF8="Fairtrade",cleaned_data!AF8="Organic (CERES)"),1, IF(OR(cleaned_data!AF8="SIZA",cleaned_data!AF8="Woolworths TNC",cleaned_data!AF8="Checkers Good Farming"),0.75, IF(cleaned_data!AF8="No Certificate",0, IF(cleaned_data!AF8="Unknown","","")))) -> 1 | T8: =IF(cleaned_data!AG8="Yes",1,0) -> 0 | U8: =IF(OR(cleaned_data!AD8="No Loan",cleaned_data!AD8="Settled",cleaned_data!AD8="Current"),1, IF(cleaned_data!AD8="In Arrears",0.5, IF(cleaned_data!AD8="Defaulted",0, IF(cleaned_data!AD8="Unknown","","")))) -> 1 | V8: {=_xlfn.IFS(cleaned_data!AE8<=0.2,1, cleaned_data!AE8<=0.5,0.75, cleaned_data!AE8<=1,0.5, cleaned_data!AE8>1,0.25)} -> 1 | W8: =IF(cleaned_data!AJ8="Yes",1,0) -> 1 | X8: {=_xlfn.IFS(cleaned_data!AM8="Yes", 1, cleaned_data!AM8="No", 0, cleaned_data!AM8="Unknown", "")} -> 1 | Y8: {=_xlfn.IFS(cleaned_data!AK8="Solar", 1, cleaned_data!AK8="Generator", 0.75, cleaned_data!AK8="Eskom grid", 0.5, TRUE, "")} -> 0.5 | Z8: {=_xlfn.IFS(cleaned_data!AL8="", "", cleaned_data!AL8<=8, 1, cleaned_data!AL8<=14, 0.75, cleaned_data!AL8<=21, 0.5, cleaned_data!AL8>=22, 0.25)} -> 0.5 | AA8: {=_xlfn.IFS(cleaned_data!AH8=0, 1, cleaned_data!AH8=1, 0.75, cleaned_data!AH8=2, 0.5, cleaned_data!AH8>=3, 0.25)} -> 0.25 | AB8: {=_xlfn.IFS(cleaned_data!AO8="", "", cleaned_data!AO8>=50, 1, cleaned_data!AO8>=30, 0.75, cleaned_data!AO8>=10, 0.5, cleaned_data!AO8<10, 0.25)} -> 1 | AC8: {=_xlfn.IFS(cleaned_data!AP8>=50,1, cleaned_data!AP8>=30,0.75, cleaned_data!AP8>=10,0.5, cleaned_data!AP8<10,0.25)} -> 1 | AD8: {=_xlfn.IFS(cleaned_data!AQ8>=30,1, cleaned_data!AQ8>=20,0.75, cleaned_data!AQ8>=10,0.5, cleaned_data!AQ8<10,0.25)} -> 0.75 | AE8: {=_xlfn.IFS(cleaned_data!AR8>=75,1, cleaned_data!AR8>=50,0.75, cleaned_data!AR8>=25,0.5, cleaned_data!AR8<25,0.25)} -> 0.5 | AF8: =IF(cleaned_data!AS8="Yes",1,0) -> 0
A9: SME0008 | B9: Ubuntu Plaas | C9: =IF(cleaned_data!K9="Registered",1,0) -> 1 | D9: =IF(cleaned_data!L9="Yes",1,0) -> 1 | E9: =IF(cleaned_data!M9="Yes",1,0) -> 1 | F9: =IF(cleaned_data!O9="Unknown","",IF(cleaned_data!O9="Yes",1,0)) -> 1 | G9: {=_xlfn.IFS(cleaned_data!N9="Owned",1,cleaned_data!N9="Leased",0.75,cleaned_data!N9="State land",0.5,cleaned_data!N9="Communal",0.25)} -> 0.75 | H9: {=_xlfn.IFS(cleaned_data!G9>=10,1,cleaned_data!G9>=5,0.75,cleaned_data!G9>=2,0.5,TRUE,0.25)} -> 1 | I9: =IF(cleaned_data!P9="None",0,1) -> 1 | J9: {=_xlfn.IFS(cleaned_data!H9>=20,1,cleaned_data!H9>=10,0.75,cleaned_data!H9>=5,0.5,cleaned_data!H9>=1,0.25,TRUE,0)} -> 1 | K9: {=_xlfn.IFS(cleaned_data!Q9>=100000,1,cleaned_data!Q9>=50000,0.75,cleaned_data!Q9>=10000,0.5,TRUE,0.25)} -> 1 | L9: {=_xlfn.IFS(cleaned_data!T9="","",cleaned_data!T9<=10,1,cleaned_data!T9<=25,0.75,cleaned_data!T9<=40,0.5, cleaned_data!T9>40,0.25)} -> 1 | M9: =IF(cleaned_data!U9="Yes",1,0) -> 1 | N9: {=_xlfn.IFS(cleaned_data!V9="Unknown","",cleaned_data!V9="Yes",1,TRUE,0)} -> 1 | O9: {=_xlfn.IFS(cleaned_data!S9>=4,1,cleaned_data!S9=3,0.75,cleaned_data!S9=2,0.5,cleaned_data!S9=1,0.25,TRUE,0)} -> 0.25 | P9: {=_xlfn.IFS(cleaned_data!AB9>=50,1,cleaned_data!AB9>=35,0.75,cleaned_data!AB9>=20,0.5,TRUE,0.25)} -> 1 | Q9: {=_xlfn.IFS(cleaned_data!X9>=5,1,cleaned_data!X9>=3,0.75,cleaned_data!X9=2,0.5,cleaned_data!X9=1,0.25,TRUE,0)} -> 1 | R9: =IF(cleaned_data!Y9="Yes",1,0) -> 0 | S9: =IF(OR(cleaned_data!AF9="GlobalG.A.P.",cleaned_data!AF9="Fairtrade",cleaned_data!AF9="Organic (CERES)"),1, IF(OR(cleaned_data!AF9="SIZA",cleaned_data!AF9="Woolworths TNC",cleaned_data!AF9="Checkers Good Farming"),0.75, IF(cleaned_data!AF9="No Certificate",0, IF(cleaned_data!AF9="Unknown","","")))) -> 1 | T9: =IF(cleaned_data!AG9="Yes",1,0) -> 1 | U9: =IF(OR(cleaned_data!AD9="No Loan",cleaned_data!AD9="Settled",cleaned_data!AD9="Current"),1, IF(cleaned_data!AD9="In Arrears",0.5, IF(cleaned_data!AD9="Defaulted",0, IF(cleaned_data!AD9="Unknown","","")))) -> 1 | V9: {=_xlfn.IFS(cleaned_data!AE9<=0.2,1, cleaned_data!AE9<=0.5,0.75, cleaned_data!AE9<=1,0.5, cleaned_data!AE9>1,0.25)} -> 1 | W9: =IF(cleaned_data!AJ9="Yes",1,0) -> 1 | X9: {=_xlfn.IFS(cleaned_data!AM9="Yes", 1, cleaned_data!AM9="No", 0, cleaned_data!AM9="Unknown", "")} -> 1 | Y9: {=_xlfn.IFS(cleaned_data!AK9="Solar", 1, cleaned_data!AK9="Generator", 0.75, cleaned_data!AK9="Eskom grid", 0.5, TRUE, "")} -> 0.5 | Z9: {=_xlfn.IFS(cleaned_data!AL9="", "", cleaned_data!AL9<=8, 1, cleaned_data!AL9<=14, 0.75, cleaned_data!AL9<=21, 0.5, cleaned_data!AL9>=22, 0.25)} -> 0.25 | AA9: {=_xlfn.IFS(cleaned_data!AH9=0, 1, cleaned_data!AH9=1, 0.75, cleaned_data!AH9=2, 0.5, cleaned_data!AH9>=3, 0.25)} -> 1 | AB9: {=_xlfn.IFS(cleaned_data!AO9="", "", cleaned_data!AO9>=50, 1, cleaned_data!AO9>=30, 0.75, cleaned_data!AO9>=10, 0.5, cleaned_data!AO9<10, 0.25)} -> 1 | AC9: {=_xlfn.IFS(cleaned_data!AP9>=50,1, cleaned_data!AP9>=30,0.75, cleaned_data!AP9>=10,0.5, cleaned_data!AP9<10,0.25)} -> 1 | AD9: {=_xlfn.IFS(cleaned_data!AQ9>=30,1, cleaned_data!AQ9>=20,0.75, cleaned_data!AQ9>=10,0.5, cleaned_data!AQ9<10,0.25)} -> 0.5 | AE9: {=_xlfn.IFS(cleaned_data!AR9>=75,1, cleaned_data!AR9>=50,0.75, cleaned_data!AR9>=25,0.5, cleaned_data!AR9<25,0.25)} -> 0.5 | AF9: =IF(cleaned_data!AS9="Yes",1,0) -> 1
A10: SME0009 | B10: Mashamba Rainbow | C10: =IF(cleaned_data!K10="Registered",1,0) -> 1 | D10: =IF(cleaned_data!L10="Yes",1,0) -> 0 | E10: =IF(cleaned_data!M10="Yes",1,0) -> 1 | F10: =IF(cleaned_data!O10="Unknown","",IF(cleaned_data!O10="Yes",1,0)) -> 1 | G10: {=_xlfn.IFS(cleaned_data!N10="Owned",1,cleaned_data!N10="Leased",0.75,cleaned_data!N10="State land",0.5,cleaned_data!N10="Communal",0.25)} -> 0.75 | H10: {=_xlfn.IFS(cleaned_data!G10>=10,1,cleaned_data!G10>=5,0.75,cleaned_data!G10>=2,0.5,TRUE,0.25)} -> 0.75 | I10: =IF(cleaned_data!P10="None",0,1) -> 1 | J10: {=_xlfn.IFS(cleaned_data!H10>=20,1,cleaned_data!H10>=10,0.75,cleaned_data!H10>=5,0.5,cleaned_data!H10>=1,0.25,TRUE,0)} -> 0.75 | K10: {=_xlfn.IFS(cleaned_data!Q10>=100000,1,cleaned_data!Q10>=50000,0.75,cleaned_data!Q10>=10000,0.5,TRUE,0.25)} -> 1 | L10: {=_xlfn.IFS(cleaned_data!T10="","",cleaned_data!T10<=10,1,cleaned_data!T10<=25,0.75,cleaned_data!T10<=40,0.5, cleaned_data!T10>40,0.25)} -> 0.75 | M10: =IF(cleaned_data!U10="Yes",1,0) -> 1 | N10: {=_xlfn.IFS(cleaned_data!V10="Unknown","",cleaned_data!V10="Yes",1,TRUE,0)} -> 1 | O10: {=_xlfn.IFS(cleaned_data!S10>=4,1,cleaned_data!S10=3,0.75,cleaned_data!S10=2,0.5,cleaned_data!S10=1,0.25,TRUE,0)} -> 0.75 | P10: {=_xlfn.IFS(cleaned_data!AB10>=50,1,cleaned_data!AB10>=35,0.75,cleaned_data!AB10>=20,0.5,TRUE,0.25)} -> 0.75 | Q10: {=_xlfn.IFS(cleaned_data!X10>=5,1,cleaned_data!X10>=3,0.75,cleaned_data!X10=2,0.5,cleaned_data!X10=1,0.25,TRUE,0)} -> 1 | R10: =IF(cleaned_data!Y10="Yes",1,0) -> 1 | S10: =IF(OR(cleaned_data!AF10="GlobalG.A.P.",cleaned_data!AF10="Fairtrade",cleaned_data!AF10="Organic (CERES)"),1, IF(OR(cleaned_data!AF10="SIZA",cleaned_data!AF10="Woolworths TNC",cleaned_data!AF10="Checkers Good Farming"),0.75, IF(cleaned_data!AF10="No Certificate",0, IF(cleaned_data!AF10="Unknown","","")))) -> 0.75 | T10: =IF(cleaned_data!AG10="Yes",1,0) -> 0 | U10: =IF(OR(cleaned_data!AD10="No Loan",cleaned_data!AD10="Settled",cleaned_data!AD10="Current"),1, IF(cleaned_data!AD10="In Arrears",0.5, IF(cleaned_data!AD10="Defaulted",0, IF(cleaned_data!AD10="Unknown","","")))) -> 1 | V10: {=_xlfn.IFS(cleaned_data!AE10<=0.2,1, cleaned_data!AE10<=0.5,0.75, cleaned_data!AE10<=1,0.5, cleaned_data!AE10>1,0.25)} -> 1 | W10: =IF(cleaned_data!AJ10="Yes",1,0) -> 1 | X10: {=_xlfn.IFS(cleaned_data!AM10="Yes", 1, cleaned_data!AM10="No", 0, cleaned_data!AM10="Unknown", "")} -> 1 | Y10: {=_xlfn.IFS(cleaned_data!AK10="Solar", 1, cleaned_data!AK10="Generator", 0.75, cleaned_data!AK10="Eskom grid", 0.5, TRUE, "")} -> 0.5 | Z10: {=_xlfn.IFS(cleaned_data!AL10="", "", cleaned_data!AL10<=8, 1, cleaned_data!AL10<=14, 0.75, cleaned_data!AL10<=21, 0.5, cleaned_data!AL10>=22, 0.25)} -> 0.5 | AA10: {=_xlfn.IFS(cleaned_data!AH10=0, 1, cleaned_data!AH10=1, 0.75, cleaned_data!AH10=2, 0.5, cleaned_data!AH10>=3, 0.25)} -> 0.75 | AB10: {=_xlfn.IFS(cleaned_data!AO10="", "", cleaned_data!AO10>=50, 1, cleaned_data!AO10>=30, 0.75, cleaned_data!AO10>=10, 0.5, cleaned_data!AO10<10, 0.25)} -> 1 | AC10: {=_xlfn.IFS(cleaned_data!AP10>=50,1, cleaned_data!AP10>=30,0.75, cleaned_data!AP10>=10,0.5, cleaned_data!AP10<10,0.25)} -> 0.5 | AD10: {=_xlfn.IFS(cleaned_data!AQ10>=30,1, cleaned_data!AQ10>=20,0.75, cleaned_data!AQ10>=10,0.5, cleaned_data!AQ10<10,0.25)} -> 1 | AE10: {=_xlfn.IFS(cleaned_data!AR10>=75,1, cleaned_data!AR10>=50,0.75, cleaned_data!AR10>=25,0.5, cleaned_data!AR10<25,0.25)} -> 0.75 | AF10: =IF(cleaned_data!AS10="Yes",1,0) -> 0
A11: SME0010 | B11: Green Valley | C11: =IF(cleaned_data!K11="Registered",1,0) -> 1 | D11: =IF(cleaned_data!L11="Yes",1,0) -> 0 | E11: =IF(cleaned_data!M11="Yes",1,0) -> 1 | F11: =IF(cleaned_data!O11="Unknown","",IF(cleaned_data!O11="Yes",1,0)) -> 1 | G11: {=_xlfn.IFS(cleaned_data!N11="Owned",1,cleaned_data!N11="Leased",0.75,cleaned_data!N11="State land",0.5,cleaned_data!N11="Communal",0.25)} -> 1 | H11: {=_xlfn.IFS(cleaned_data!G11>=10,1,cleaned_data!G11>=5,0.75,cleaned_data!G11>=2,0.5,TRUE,0.25)} -> 1 | I11: =IF(cleaned_data!P11="None",0,1) -> 1 | J11: {=_xlfn.IFS(cleaned_data!H11>=20,1,cleaned_data!H11>=10,0.75,cleaned_data!H11>=5,0.5,cleaned_data!H11>=1,0.25,TRUE,0)} -> 1 | K11: {=_xlfn.IFS(cleaned_data!Q11>=100000,1,cleaned_data!Q11>=50000,0.75,cleaned_data!Q11>=10000,0.5,TRUE,0.25)} -> 0.25 | L11: {=_xlfn.IFS(cleaned_data!T11="","",cleaned_data!T11<=10,1,cleaned_data!T11<=25,0.75,cleaned_data!T11<=40,0.5, cleaned_data!T11>40,0.25)} -> 1 | M11: =IF(cleaned_data!U11="Yes",1,0) -> 1 | N11: {=_xlfn.IFS(cleaned_data!V11="Unknown","",cleaned_data!V11="Yes",1,TRUE,0)} -> 1 | O11: {=_xlfn.IFS(cleaned_data!S11>=4,1,cleaned_data!S11=3,0.75,cleaned_data!S11=2,0.5,cleaned_data!S11=1,0.25,TRUE,0)} -> 1 | P11: {=_xlfn.IFS(cleaned_data!AB11>=50,1,cleaned_data!AB11>=35,0.75,cleaned_data!AB11>=20,0.5,TRUE,0.25)} -> 0.75 | Q11: {=_xlfn.IFS(cleaned_data!X11>=5,1,cleaned_data!X11>=3,0.75,cleaned_data!X11=2,0.5,cleaned_data!X11=1,0.25,TRUE,0)} -> 1 | R11: =IF(cleaned_data!Y11="Yes",1,0) -> 1 | S11: =IF(OR(cleaned_data!AF11="GlobalG.A.P.",cleaned_data!AF11="Fairtrade",cleaned_data!AF11="Organic (CERES)"),1, IF(OR(cleaned_data!AF11="SIZA",cleaned_data!AF11="Woolworths TNC",cleaned_data!AF11="Checkers Good Farming"),0.75, IF(cleaned_data!AF11="No Certificate",0, IF(cleaned_data!AF11="Unknown","","")))) -> 0.75 | T11: =IF(cleaned_data!AG11="Yes",1,0) -> 0 | U11: =IF(OR(cleaned_data!AD11="No Loan",cleaned_data!AD11="Settled",cleaned_data!AD11="Current"),1, IF(cleaned_data!AD11="In Arrears",0.5, IF(cleaned_data!AD11="Defaulted",0, IF(cleaned_data!AD11="Unknown","","")))) -> 1 | V11: {=_xlfn.IFS(cleaned_data!AE11<=0.2,1, cleaned_data!AE11<=0.5,0.75, cleaned_data!AE11<=1,0.5, cleaned_data!AE11>1,0.25)} -> 0.25 | W11: =IF(cleaned_data!AJ11="Yes",1,0) -> 1 | X11: {=_xlfn.IFS(cleaned_data!AM11="Yes", 1, cleaned_data!AM11="No", 0, cleaned_data!AM11="Unknown", "")} -> 1 | Y11: {=_xlfn.IFS(cleaned_data!AK11="Solar", 1, cleaned_data!AK11="Generator", 0.75, cleaned_data!AK11="Eskom grid", 0.5, TRUE, "")} -> 0.75 | Z11: {=_xlfn.IFS(cleaned_data!AL11="", "", cleaned_data!AL11<=8, 1, cleaned_data!AL11<=14, 0.75, cleaned_data!AL11<=21, 0.5, cleaned_data!AL11>=22, 0.25)} -> 1 | AA11: {=_xlfn.IFS(cleaned_data!AH11=0, 1, cleaned_data!AH11=1, 0.75, cleaned_data!AH11=2, 0.5, cleaned_data!AH11>=3, 0.25)} -> 1 | AB11: {=_xlfn.IFS(cleaned_data!AO11="", "", cleaned_data!AO11>=50, 1, cleaned_data!AO11>=30, 0.75, cleaned_data!AO11>=10, 0.5, cleaned_data!AO11<10, 0.25)} -> 1 | AC11: {=_xlfn.IFS(cleaned_data!AP11>=50,1, cleaned_data!AP11>=30,0.75, cleaned_data!AP11>=10,0.5, cleaned_data!AP11<10,0.25)} -> 0.5 | AD11: {=_xlfn.IFS(cleaned_data!AQ11>=30,1, cleaned_data!AQ11>=20,0.75, cleaned_data!AQ11>=10,0.5, cleaned_data!AQ11<10,0.25)} -> 1 | AE11: {=_xlfn.IFS(cleaned_data!AR11>=75,1, cleaned_data!AR11>=50,0.75, cleaned_data!AR11>=25,0.5, cleaned_data!AR11<25,0.25)} -> 0.75 | AF11: =IF(cleaned_data!AS11="Yes",1,0) -> 0
A12: SME0011 | B12: Siyabonga Plaas | C12: =IF(cleaned_data!K12="Registered",1,0) -> 1 | D12: =IF(cleaned_data!L12="Yes",1,0) -> 1 | E12: =IF(cleaned_data!M12="Yes",1,0) -> 1 | F12: =IF(cleaned_data!O12="Unknown","",IF(cleaned_data!O12="Yes",1,0)) | G12: {=_xlfn.IFS(cleaned_data!N12="Owned",1,cleaned_data!N12="Leased",0.75,cleaned_data!N12="State land",0.5,cleaned_data!N12="Communal",0.25)} -> 1 | H12: {=_xlfn.IFS(cleaned_data!G12>=10,1,cleaned_data!G12>=5,0.75,cleaned_data!G12>=2,0.5,TRUE,0.25)} -> 1 | I12: =IF(cleaned_data!P12="None",0,1) -> 1 | J12: {=_xlfn.IFS(cleaned_data!H12>=20,1,cleaned_data!H12>=10,0.75,cleaned_data!H12>=5,0.5,cleaned_data!H12>=1,0.25,TRUE,0)} -> 1 | K12: {=_xlfn.IFS(cleaned_data!Q12>=100000,1,cleaned_data!Q12>=50000,0.75,cleaned_data!Q12>=10000,0.5,TRUE,0.25)} -> 1 | L12: {=_xlfn.IFS(cleaned_data!T12="","",cleaned_data!T12<=10,1,cleaned_data!T12<=25,0.75,cleaned_data!T12<=40,0.5, cleaned_data!T12>40,0.25)} -> 0.75 | M12: =IF(cleaned_data!U12="Yes",1,0) -> 1 | N12: {=_xlfn.IFS(cleaned_data!V12="Unknown","",cleaned_data!V12="Yes",1,TRUE,0)} -> 1 | O12: {=_xlfn.IFS(cleaned_data!S12>=4,1,cleaned_data!S12=3,0.75,cleaned_data!S12=2,0.5,cleaned_data!S12=1,0.25,TRUE,0)} -> 0.5 | P12: {=_xlfn.IFS(cleaned_data!AB12>=50,1,cleaned_data!AB12>=35,0.75,cleaned_data!AB12>=20,0.5,TRUE,0.25)} -> 0.75 | Q12: {=_xlfn.IFS(cleaned_data!X12>=5,1,cleaned_data!X12>=3,0.75,cleaned_data!X12=2,0.5,cleaned_data!X12=1,0.25,TRUE,0)} -> 0.75 | R12: =IF(cleaned_data!Y12="Yes",1,0) -> 0 | S12: =IF(OR(cleaned_data!AF12="GlobalG.A.P.",cleaned_data!AF12="Fairtrade",cleaned_data!AF12="Organic (CERES)"),1, IF(OR(cleaned_data!AF12="SIZA",cleaned_data!AF12="Woolworths TNC",cleaned_data!AF12="Checkers Good Farming"),0.75, IF(cleaned_data!AF12="No Certificate",0, IF(cleaned_data!AF12="Unknown","","")))) -> 1 | T12: =IF(cleaned_data!AG12="Yes",1,0) -> 0 | U12: =IF(OR(cleaned_data!AD12="No Loan",cleaned_data!AD12="Settled",cleaned_data!AD12="Current"),1, IF(cleaned_data!AD12="In Arrears",0.5, IF(cleaned_data!AD12="Defaulted",0, IF(cleaned_data!AD12="Unknown","","")))) -> 0.5 | V12: {=_xlfn.IFS(cleaned_data!AE12<=0.2,1, cleaned_data!AE12<=0.5,0.75, cleaned_data!AE12<=1,0.5, cleaned_data!AE12>1,0.25)} -> 1 | W12: =IF(cleaned_data!AJ12="Yes",1,0) -> 1 | X12: {=_xlfn.IFS(cleaned_data!AM12="Yes", 1, cleaned_data!AM12="No", 0, cleaned_data!AM12="Unknown", "")} -> 1 | Y12: {=_xlfn.IFS(cleaned_data!AK12="Solar", 1, cleaned_data!AK12="Generator", 0.75, cleaned_data!AK12="Eskom grid", 0.5, TRUE, "")} -> 1 | Z12: {=_xlfn.IFS(cleaned_data!AL12="", "", cleaned_data!AL12<=8, 1, cleaned_data!AL12<=14, 0.75, cleaned_data!AL12<=21, 0.5, cleaned_data!AL12>=22, 0.25)} -> 1 | AA12: {=_xlfn.IFS(cleaned_data!AH12=0, 1, cleaned_data!AH12=1, 0.75, cleaned_data!AH12=2, 0.5, cleaned_data!AH12>=3, 0.25)} -> 1 | AB12: {=_xlfn.IFS(cleaned_data!AO12="", "", cleaned_data!AO12>=50, 1, cleaned_data!AO12>=30, 0.75, cleaned_data!AO12>=10, 0.5, cleaned_data!AO12<10, 0.25)} -> 0.75 | AC12: {=_xlfn.IFS(cleaned_data!AP12>=50,1, cleaned_data!AP12>=30,0.75, cleaned_data!AP12>=10,0.5, cleaned_data!AP12<10,0.25)} -> 0.5 | AD12: {=_xlfn.IFS(cleaned_data!AQ12>=30,1, cleaned_data!AQ12>=20,0.75, cleaned_data!AQ12>=10,0.5, cleaned_data!AQ12<10,0.25)} -> 1 | AE12: {=_xlfn.IFS(cleaned_data!AR12>=75,1, cleaned_data!AR12>=50,0.75, cleaned_data!AR12>=25,0.5, cleaned_data!AR12<25,0.25)} -> 0.5 | AF12: =IF(cleaned_data!AS12="Yes",1,0) -> 0
A13: SME0012 | B13: Silver Valley | C13: =IF(cleaned_data!K13="Registered",1,0) -> 1 | D13: =IF(cleaned_data!L13="Yes",1,0) -> 1 | E13: =IF(cleaned_data!M13="Yes",1,0) -> 1 | F13: =IF(cleaned_data!O13="Unknown","",IF(cleaned_data!O13="Yes",1,0)) -> 1 | G13: {=_xlfn.IFS(cleaned_data!N13="Owned",1,cleaned_data!N13="Leased",0.75,cleaned_data!N13="State land",0.5,cleaned_data!N13="Communal",0.25)} -> 1 | H13: {=_xlfn.IFS(cleaned_data!G13>=10,1,cleaned_data!G13>=5,0.75,cleaned_data!G13>=2,0.5,TRUE,0.25)} -> 1 | I13: =IF(cleaned_data!P13="None",0,1) -> 1 | J13: {=_xlfn.IFS(cleaned_data!H13>=20,1,cleaned_data!H13>=10,0.75,cleaned_data!H13>=5,0.5,cleaned_data!H13>=1,0.25,TRUE,0)} -> 1 | K13: {=_xlfn.IFS(cleaned_data!Q13>=100000,1,cleaned_data!Q13>=50000,0.75,cleaned_data!Q13>=10000,0.5,TRUE,0.25)} -> 1 | L13: {=_xlfn.IFS(cleaned_data!T13="","",cleaned_data!T13<=10,1,cleaned_data!T13<=25,0.75,cleaned_data!T13<=40,0.5, cleaned_data!T13>40,0.25)} -> 0.75 | M13: =IF(cleaned_data!U13="Yes",1,0) -> 1 | N13: {=_xlfn.IFS(cleaned_data!V13="Unknown","",cleaned_data!V13="Yes",1,TRUE,0)} -> 0 | O13: {=_xlfn.IFS(cleaned_data!S13>=4,1,cleaned_data!S13=3,0.75,cleaned_data!S13=2,0.5,cleaned_data!S13=1,0.25,TRUE,0)} -> 1 | P13: {=_xlfn.IFS(cleaned_data!AB13>=50,1,cleaned_data!AB13>=35,0.75,cleaned_data!AB13>=20,0.5,TRUE,0.25)} -> 0.75 | Q13: {=_xlfn.IFS(cleaned_data!X13>=5,1,cleaned_data!X13>=3,0.75,cleaned_data!X13=2,0.5,cleaned_data!X13=1,0.25,TRUE,0)} -> 1 | R13: =IF(cleaned_data!Y13="Yes",1,0) -> 1 | S13: =IF(OR(cleaned_data!AF13="GlobalG.A.P.",cleaned_data!AF13="Fairtrade",cleaned_data!AF13="Organic (CERES)"),1, IF(OR(cleaned_data!AF13="SIZA",cleaned_data!AF13="Woolworths TNC",cleaned_data!AF13="Checkers Good Farming"),0.75, IF(cleaned_data!AF13="No Certificate",0, IF(cleaned_data!AF13="Unknown","","")))) -> 1 | T13: =IF(cleaned_data!AG13="Yes",1,0) -> 0 | U13: =IF(OR(cleaned_data!AD13="No Loan",cleaned_data!AD13="Settled",cleaned_data!AD13="Current"),1, IF(cleaned_data!AD13="In Arrears",0.5, IF(cleaned_data!AD13="Defaulted",0, IF(cleaned_data!AD13="Unknown","","")))) -> 1 | V13: {=_xlfn.IFS(cleaned_data!AE13<=0.2,1, cleaned_data!AE13<=0.5,0.75, cleaned_data!AE13<=1,0.5, cleaned_data!AE13>1,0.25)} -> 1 | W13: =IF(cleaned_data!AJ13="Yes",1,0) -> 1 | X13: {=_xlfn.IFS(cleaned_data!AM13="Yes", 1, cleaned_data!AM13="No", 0, cleaned_data!AM13="Unknown", "")} -> 1 | Y13: {=_xlfn.IFS(cleaned_data!AK13="Solar", 1, cleaned_data!AK13="Generator", 0.75, cleaned_data!AK13="Eskom grid", 0.5, TRUE, "")} -> 0.5 | Z13: {=_xlfn.IFS(cleaned_data!AL13="", "", cleaned_data!AL13<=8, 1, cleaned_data!AL13<=14, 0.75, cleaned_data!AL13<=21, 0.5, cleaned_data!AL13>=22, 0.25)} -> 0.5 | AA13: {=_xlfn.IFS(cleaned_data!AH13=0, 1, cleaned_data!AH13=1, 0.75, cleaned_data!AH13=2, 0.5, cleaned_data!AH13>=3, 0.25)} -> 0.5 | AB13: {=_xlfn.IFS(cleaned_data!AO13="", "", cleaned_data!AO13>=50, 1, cleaned_data!AO13>=30, 0.75, cleaned_data!AO13>=10, 0.5, cleaned_data!AO13<10, 0.25)} -> 1 | AC13: {=_xlfn.IFS(cleaned_data!AP13>=50,1, cleaned_data!AP13>=30,0.75, cleaned_data!AP13>=10,0.5, cleaned_data!AP13<10,0.25)} -> 0.5 | AD13: {=_xlfn.IFS(cleaned_data!AQ13>=30,1, cleaned_data!AQ13>=20,0.75, cleaned_data!AQ13>=10,0.5, cleaned_data!AQ13<10,0.25)} -> 0.5 | AE13: {=_xlfn.IFS(cleaned_data!AR13>=75,1, cleaned_data!AR13>=50,0.75, cleaned_data!AR13>=25,0.5, cleaned_data!AR13<25,0.25)} -> 0.75 | AF13: =IF(cleaned_data!AS13="Yes",1,0) -> 1
... A151: SME0150 | B151: Andile Green | C151: =IF(cleaned_data!K151="Registered",1,0) -> 0 | D151: =IF(cleaned_data!L151="Yes",1,0) -> 0 | E151: =IF(cleaned_data!M151="Yes",1,0) -> 1 | F151: =IF(cleaned_data!O151="Unknown","",IF(cleaned_data!O151="Yes",1,0)) | G151: {=_xlfn.IFS(cleaned_data!N151="Owned",1,cleaned_data!N151="Leased",0.75,cleaned_data!N151="State land",0.5,cleaned_data!N151="Communal",0.25)} -> 0.75 | H151: {=_xlfn.IFS(cleaned_data!G151>=10,1,cleaned_data!G151>=5,0.75,cleaned_data!G151>=2,0.5,TRUE,0.25)} -> 0.75 | I151: =IF(cleaned_data!P151="None",0,1) -> 1 | J151: {=_xlfn.IFS(cleaned_data!H151>=20,1,cleaned_data!H151>=10,0.75,cleaned_data!H151>=5,0.5,cleaned_data!H151>=1,0.25,TRUE,0)} -> 1 | K151: {=_xlfn.IFS(cleaned_data!Q151>=100000,1,cleaned_data!Q151>=50000,0.75,cleaned_data!Q151>=10000,0.5,TRUE,0.25)} -> 0.75 | L151: {=_xlfn.IFS(cleaned_data!T151="","",cleaned_data!T151<=10,1,cleaned_data!T151<=25,0.75,cleaned_data!T151<=40,0.5, cleaned_data!T151>40,0.25)} -> 0.75 | M151: =IF(cleaned_data!U151="Yes",1,0) -> 1 | N151: {=_xlfn.IFS(cleaned_data!V151="Unknown","",cleaned_data!V151="Yes",1,TRUE,0)} -> 0 | O151: {=_xlfn.IFS(cleaned_data!S151>=4,1,cleaned_data!S151=3,0.75,cleaned_data!S151=2,0.5,cleaned_data!S151=1,0.25,TRUE,0)} -> 0.75 | P151: {=_xlfn.IFS(cleaned_data!AB151>=50,1,cleaned_data!AB151>=35,0.75,cleaned_data!AB151>=20,0.5,TRUE,0.25)} -> 0.5 | Q151: {=_xlfn.IFS(cleaned_data!X151>=5,1,cleaned_data!X151>=3,0.75,cleaned_data!X151=2,0.5,cleaned_data!X151=1,0.25,TRUE,0)} -> 0.75 | R151: =IF(cleaned_data!Y151="Yes",1,0) -> 1 | S151: =IF(OR(cleaned_data!AF151="GlobalG.A.P.",cleaned_data!AF151="Fairtrade",cleaned_data!AF151="Organic (CERES)"),1, IF(OR(cleaned_data!AF151="SIZA",cleaned_data!AF151="Woolworths TNC",cleaned_data!AF151="Checkers Good Farming"),0.75, IF(cleaned_data!AF151="No Certificate",0, IF(cleaned_data!AF151="Unknown","","")))) -> 0 | T151: =IF(cleaned_data!AG151="Yes",1,0) -> 0 | U151: =IF(OR(cleaned_data!AD151="No Loan",cleaned_data!AD151="Settled",cleaned_data!AD151="Current"),1, IF(cleaned_data!AD151="In Arrears",0.5, IF(cleaned_data!AD151="Defaulted",0, IF(cleaned_data!AD151="Unknown","","")))) -> 0 | V151: {=_xlfn.IFS(cleaned_data!AE151<=0.2,1, cleaned_data!AE151<=0.5,0.75, cleaned_data!AE151<=1,0.5, cleaned_data!AE151>1,0.25)} -> 1 | W151: =IF(cleaned_data!AJ151="Yes",1,0) -> 1 | X151: {=_xlfn.IFS(cleaned_data!AM151="Yes", 1, cleaned_data!AM151="No", 0, cleaned_data!AM151="Unknown", "")} -> 0 | Y151: {=_xlfn.IFS(cleaned_data!AK151="Solar", 1, cleaned_data!AK151="Generator", 0.75, cleaned_data!AK151="Eskom grid", 0.5, TRUE, "")} -> 0.5 | Z151: {=_xlfn.IFS(cleaned_data!AL151="", "", cleaned_data!AL151<=8, 1, cleaned_data!AL151<=14, 0.75, cleaned_data!AL151<=21, 0.5, cleaned_data!AL151>=22, 0.25)} -> 0.5 | AA151: {=_xlfn.IFS(cleaned_data!AH151=0, 1, cleaned_data!AH151=1, 0.75, cleaned_data!AH151=2, 0.5, cleaned_data!AH151>=3, 0.25)} -> 0.5 | AB151: {=_xlfn.IFS(cleaned_data!AO151="", "", cleaned_data!AO151>=50, 1, cleaned_data!AO151>=30, 0.75, cleaned_data!AO151>=10, 0.5, cleaned_data!AO151<10, 0.25)} -> 0.75 | AC151: {=_xlfn.IFS(cleaned_data!AP151>=50,1, cleaned_data!AP151>=30,0.75, cleaned_data!AP151>=10,0.5, cleaned_data!AP151<10,0.25)} -> 0.75 | AD151: {=_xlfn.IFS(cleaned_data!AQ151>=30,1, cleaned_data!AQ151>=20,0.75, cleaned_data!AQ151>=10,0.5, cleaned_data!AQ151<10,0.25)} -> 1 | AE151: {=_xlfn.IFS(cleaned_data!AR151>=75,1, cleaned_data!AR151>=50,0.75, cleaned_data!AR151>=25,0.5, cleaned_data!AR151<25,0.25)} -> 1 | AF151: =IF(cleaned_data!AS151="Yes",1,0) -> 0

Sheet Pillar_Scores
A1: sme_id | B1: sme_name | C1: Governance & Identity | D1: Production Capacity | E1: Market Access & Financial Viability | F1: Climate & Shock Resilience | G1: Social Impact & Gender Inclusion
A2: SME0001 | B2: Thando Boerdery | C2: =AVERAGE(Score_Calculations!C2:J2)*20 -> 20 | D2: =AVERAGE(Score_Calculations!K2:O2)*20 -> 20 | E2: =AVERAGE(Score_Calculations!P2:V2)*30 -> 27.857143 | F2: =AVERAGE(Score_Calculations!W2:AA2)*15 -> 10.5 | G2: =AVERAGE(Score_Calculations!AB2:AF2)*15 -> 7.5
A3: SME0002 | B3: Tlhaga Morning | C3: =AVERAGE(Score_Calculations!C3:J3)*20 -> 18.75 | D3: =AVERAGE(Score_Calculations!K3:O3)*20 -> 19 | E3: =AVERAGE(Score_Calculations!P3:V3)*30 -> 25 | F3: =AVERAGE(Score_Calculations!W3:AA3)*15 -> 12 | G3: =AVERAGE(Score_Calculations!AB3:AF3)*15 -> 10.5
A4: SME0003 | B4: Vhembe Red | C4: =AVERAGE(Score_Calculations!C4:J4)*20 -> 16.25 | D4: =AVERAGE(Score_Calculations!K4:O4)*20 -> 17 | E4: =AVERAGE(Score_Calculations!P4:V4)*30 -> 27.857143 | F4: =AVERAGE(Score_Calculations!W4:AA4)*15 -> 15 | G4: =AVERAGE(Score_Calculations!AB4:AF4)*15 -> 9.75
A5: SME0004 | B5: Tsebo Red | C5: =AVERAGE(Score_Calculations!C5:J5)*20 -> 20 | D5: =AVERAGE(Score_Calculations!K5:O5)*20 -> 18.75 | E5: =AVERAGE(Score_Calculations!P5:V5)*30 -> 26.785714 | F5: =AVERAGE(Score_Calculations!W5:AA5)*15 -> 6 | G5: =AVERAGE(Score_Calculations!AB5:AF5)*15 -> 10.5
A6: SME0005 | B6: Silver Valley | C6: =AVERAGE(Score_Calculations!C6:J6)*20 -> 19.375 | D6: =AVERAGE(Score_Calculations!K6:O6)*20 -> 16 | E6: =AVERAGE(Score_Calculations!P6:V6)*30 -> 24.642857 | F6: =AVERAGE(Score_Calculations!W6:AA6)*15 -> 11.25 | G6: =AVERAGE(Score_Calculations!AB6:AF6)*15 -> 10.5
A7: SME0006 | B7: Tshivhase Silver | C7: =AVERAGE(Score_Calculations!C7:J7)*20 -> 11.25 | D7: =AVERAGE(Score_Calculations!K7:O7)*20 -> 9 | E7: =AVERAGE(Score_Calculations!P7:V7)*30 -> 27.857143 | F7: =AVERAGE(Score_Calculations!W7:AA7)*15 -> 12.75 | G7: =AVERAGE(Score_Calculations!AB7:AF7)*15 -> 12
A8: SME0007 | B8: Amandla Golden | C8: =AVERAGE(Score_Calculations!C8:J8)*20 -> 19.285714 | D8: =AVERAGE(Score_Calculations!K8:O8)*20 -> 11 | E8: =AVERAGE(Score_Calculations!P8:V8)*30 -> 24.642857 | F8: =AVERAGE(Score_Calculations!W8:AA8)*15 -> 9.75 | G8: =AVERAGE(Score_Calculations!AB8:AF8)*15 -> 9.75
A9: SME0008 | B9: Ubuntu Plaas | C9: =AVERAGE(Score_Calculations!C9:J9)*20 -> 19.375 | D9: =AVERAGE(Score_Calculations!K9:O9)*20 -> 17 | E9: =AVERAGE(Score_Calculations!P9:V9)*30 -> 25.714286 | F9: =AVERAGE(Score_Calculations!W9:AA9)*15 -> 11.25 | G9: =AVERAGE(Score_Calculations!AB9:AF9)*15 -> 12
A10: SME0009 | B10: Mashamba Rainbow | C10: =AVERAGE(Score_Calculations!C10:J10)*20 -> 15.625 | D10: =AVERAGE(Score_Calculations!K10:O10)*20 -> 18 | E10: =AVERAGE(Score_Calculations!P10:V10)*30 -> 23.571429 | F10: =AVERAGE(Score_Calculations!W10:AA10)*15 -> 11.25 | G10: =AVERAGE(Score_Calculations!AB10:AF10)*15 -> 9.75
A11: SME0010 | B11: Green Valley | C11: =AVERAGE(Score_Calculations!C11:J11)*20 -> 17.5 | D11: =AVERAGE(Score_Calculations!K11:O11)*20 -> 17 | E11: =AVERAGE(Score_Calculations!P11:V11)*30 -> 20.357143 | F11: =AVERAGE(Score_Calculations!W11:AA11)*15 -> 14.25 | G11: =AVERAGE(Score_Calculations!AB11:AF11)*15 -> 9.75
A12: SME0011 | B12: Siyabonga Plaas | C12: =AVERAGE(Score_Calculations!C12:J12)*20 -> 20 | D12: =AVERAGE(Score_Calculations!K12:O12)*20 -> 17 | E12: =AVERAGE(Score_Calculations!P12:V12)*30 -> 17.142857 | F12: =AVERAGE(Score_Calculations!W12:AA12)*15 -> 15 | G12: =AVERAGE(Score_Calculations!AB12:AF12)*15 -> 8.25
A13: SME0012 | B13: Silver Valley | C13: =AVERAGE(Score_Calculations!C13:J13)*20 -> 20 | D13: =AVERAGE(Score_Calculations!K13:O13)*20 -> 15 | E13: =AVERAGE(Score_Calculations!P13:V13)*30 -> 24.642857 | F13: =AVERAGE(Score_Calculations!W13:AA13)*15 -> 10.5 | G13: =AVERAGE(Score_Calculations!AB13:AF13)*15 -> 11.25
... A151: SME0150 | B151: Andile Green | C151: =AVERAGE(Score_Calculations!C151:J151)*20 -> 12.857143 | D151: =AVERAGE(Score_Calculations!K151:O151)*20 -> 13 | E151: =AVERAGE(Score_Calculations!P151:V151)*30 -> 13.928571 | F151: =AVERAGE(Score_Calculations!W151:AA151)*15 -> 7.5 | G151: =AVERAGE(Score_Calculations!AB151:AF151)*15 -> 10.5

Sheet Final_Ranking
A1: sme_id | B1: sme_name | C1: Governance & Identity | D1: Production Capacity | E1: Market Access & Financial Viability | F1: Climate & Shock Resilience | G1: Social Impact & Gender Inclusion | H1: Final Score | I1: Rank | J1: Classification
A2: SME0017 | B2: Tshivhase Siyabonga | C2: 17.5 | D2: 20 | E2: 30 | F2: 10.5 | G2: 12 | H2: =SUM(C2:G2) -> 90 | I2: =_xlfn.RANK.EQ(H2,$H$2:$H$151,0) -> 1 | J2: {=_xlfn.IFS( H2>=80," Investment Ready", H2>=60," Emerging Potential", H2>=40," Needs Capacity Support ", TRUE,"High Risk")} -> Investment Ready
A3: SME0033 | B3: Lentswe Morning | C3: 20 | D3: 19 | E3: 27.857143 | F3: 12.75 | G3: 9 | H3: =SUM(C3:G3) -> 88.607143 | I3: =_xlfn.RANK.EQ(H3,$H$2:$H$151,0) -> 2 | J3: {=_xlfn.IFS( H3>=80," Investment Ready", H3>=60," Emerging Potential", H3>=40," Needs Capacity Support ", TRUE,"High Risk")} -> Investment Ready
A4: SME0037 | B4: Tlhaga Blue | C4: 20 | D4: 19 | E4: 25.714286 | F4: 15 | G4: 8.25 | H4: =SUM(C4:G4) -> 87.964286 | I4: =_xlfn.RANK.EQ(H4,$H$2:$H$151,0) -> 3 | J4: {=_xlfn.IFS( H4>=80," Investment Ready", H4>=60," Emerging Potential", H4>=40," Needs Capacity Support ", TRUE,"High Risk")} -> Investment Ready
A5: SME0021 | B5: Tlhaga Blue | C5: 16.875 | D5: 19 | E5: 27.857143 | F5: 12.75 | G5: 11.25 | H5: =SUM(C5:G5) -> 87.732143 | I5: =_xlfn.RANK.EQ(H5,$H$2:$H$151,0) -> 4 | J5: {=_xlfn.IFS( H5>=80," Investment Ready", H5>=60," Emerging Potential", H5>=40," Needs Capacity Support ", TRUE,"High Risk")} -> Investment Ready
A6: SME0018 | B6: Mupo Green | C6: 15 | D6: 17 | E6: 30 | F6: 13.5 | G6: 12 | H6: =SUM(C6:G6) -> 87.5 | I6: =_xlfn.RANK.EQ(H6,$H$2:$H$151,0) -> 5 | J6: {=_xlfn.IFS( H6>=80," Investment Ready", H6>=60," Emerging Potential", H6>=40," Needs Capacity Support ", TRUE,"High Risk")} -> Investment Ready
A7: SME0001 | B7: Thando Boerdery | C7: 20 | D7: 20 | E7: 27.857143 | F7: 10.5 | G7: 7.5 | H7: =SUM(C7:G7) -> 85.857143 | I7: =_xlfn.RANK.EQ(H7,$H$2:$H$151,0) -> 6 | J7: {=_xlfn.IFS( H7>=80," Investment Ready", H7>=60," Emerging Potential", H7>=40," Needs Capacity Support ", TRUE,"High Risk")} -> Investment Ready
A8: SME0003 | B8: Vhembe Red | C8: 16.25 | D8: 17 | E8: 27.857143 | F8: 15 | G8: 9.75 | H8: =SUM(C8:G8) -> 85.857143 | I8: =_xlfn.RANK.EQ(H8,$H$2:$H$151,0) -> 6 | J8: {=_xlfn.IFS( H8>=80," Investment Ready", H8>=60," Emerging Potential", H8>=40," Needs Capacity Support ", TRUE,"High Risk")} -> Investment Ready
A9: SME0008 | B9: Ubuntu Plaas | C9: 19.375 | D9: 17 | E9: 25.714286 | F9: 11.25 | G9: 12 | H9: =SUM(C9:G9) -> 85.339286 | I9: =_xlfn.RANK.EQ(H9,$H$2:$H$151,0) -> 8 | J9: {=_xlfn.IFS( H9>=80," Investment Ready", H9>=60," Emerging Potential", H9>=40," Needs Capacity Support ", TRUE,"High Risk")} -> Investment Ready
A10: SME0002 | B10: Tlhaga Morning | C10: 18.75 | D10: 19 | E10: 25 | F10: 12 | G10: 10.5 | H10: =SUM(C10:G10) -> 85.25 | I10: =_xlfn.RANK.EQ(H10,$H$2:$H$151,0) -> 9 | J10: {=_xlfn.IFS( H10>=80," Investment Ready", H10>=60," Emerging Potential", H10>=40," Needs Capacity Support ", TRUE,"High Risk")} -> Investment Ready
A11: SME0028 | B11: Mashamba Rainbow | C11: 20 | D11: 16 | E11: 28.928571 | F11: 12 | G11: 8.25 | H11: =SUM(C11:G11) -> 85.178571 | I11: =_xlfn.RANK.EQ(H11,$H$2:$H$151,0) -> 10 | J11: {=_xlfn.IFS( H11>=80," Investment Ready", H11>=60," Emerging Potential", H11>=40," Needs Capacity Support ", TRUE,"High Risk")} -> Investment Ready
A12: SME0038 | B12: Kopano Ubuntu | C12: 18.75 | D12: 18.75 | E12: 22.5 | F12: 12 | G12: 12.75 | H12: =SUM(C12:G12) -> 84.75 | I12: =_xlfn.RANK.EQ(H12,$H$2:$H$151,0) -> 11 | J12: {=_xlfn.IFS( H12>=80," Investment Ready", H12>=60," Emerging Potential", H12>=40," Needs Capacity Support ", TRUE,"High Risk")} -> Investment Ready
A13: SME0041 | B13: Tshivhase Old | C13: 19.375 | D13: 19 | E13: 24.642857 | F13: 8.25 | G13: 12.75 | H13: =SUM(C13:G13) -> 84.017857 | I13: =_xlfn.RANK.EQ(H13,$H$2:$H$151,0) -> 12 | J13: {=_xlfn.IFS( H13>=80," Investment Ready", H13>=60," Emerging Potential", H13>=40," Needs Capacity Support ", TRUE,"High Risk")} -> Investment Ready
... A151: SME0145 | B151: New Farm | C151: 11.25 | D151: 8 | E151: 7.5 | F151: 4.5 | G151: 8.25 | H151: =SUM(C151:G151) -> 39.5 | I151: =_xlfn.RANK.EQ(H151,$H$2:$H$151,0) -> 150 | J151: {=_xlfn.IFS( H151>=80," Investment Ready", H151>=60," Emerging Potential", H151>=40," Needs Capacity Support ", TRUE,"High Risk")} -> High Risk
